[{"imgUrl": "https://static.massimodutti.net/3/photos//2023/V/0/1/p/6693/870/800/01/6693870800_2_7_16.jpg?t=1681205106547&impolicy=massimodutti-itxmediumhigh&imwidth=200&imformat=chrome", "title": "Kalp yaka siyah elbise", "price": "2.299,00 TL"}, {"imgUrl": "https://static.massimodutti.net/3/photos//2023/V/0/1/p/6600/100/250/6600100250_8_9_16.jpg?t=1678185678554&impolicy=massimodutti-itxmediumhigh&imwidth=200&imformat=chrome", "title": "Keten kar\u0131\u015f\u0131ml\u0131 diki\u015fli g\u00f6mlek elbise", "price": "2.099,00 TL"}, {"imgUrl": "https://static.massimodutti.net/3/photos//2023/V/0/1/p/6795/101/305/02/6795101305_8_9_16.jpg?t=1678185668023&impolicy=massimodutti-itxmediumhigh&imwidth=200&imformat=chrome", "title": "Keten kaftan elbise", "price": "2.299,00 TL"}, {"imgUrl": "https://static.massimodutti.net/3/photos//2023/V/0/1/p/6795/101/305/6795101305_2_5_16.jpg?t=1675351514836&impolicy=massimodutti-itxmediumhigh&imwidth=200&imformat=chrome", "title": "Keten kaftan elbise", "price": "2.299,00 TL"}, {"imgUrl": "https://static.massimodutti.net/3/photos//2023/V/0/1/p/6795/101/250/6795101250_2_5_16.jpg?t=1675351514755&impolicy=massimodutti-itxmediumhigh&imwidth=200&imformat=chrome", "title": "Keten kaftan elbise", "price": "2.299,00 TL"}, {"imgUrl": "https://static.massimodutti.net/3/photos//2023/V/0/1/p/6638/703/798/6638703798_2_5_16.jpg?t=1675351528339&impolicy=massimodutti-itxmediumhigh&imwidth=200&imformat=chrome", "title": "Keten tulum", "price": "1.999,00 TL"}, {"imgUrl": "https://static.massimodutti.net/3/photos//2023/V/0/1/p/6637/737/700/6637737700_2_5_16.jpg?t=1678364744706&impolicy=massimodutti-itxmediumhigh&imwidth=200&imformat=chrome", "title": "%100 keten \u00e7izgili rustik elbise", "price": "2.099,00 TL"}, {"imgUrl": "https://static.massimodutti.net/3/photos//2023/V/0/1/p/6669/100/711/6669100711_2_5_16.jpg?t=1679307208798&impolicy=massimodutti-itxmediumhigh&imwidth=200&imformat=chrome", "title": "\u00c7apraz ba\u011fc\u0131kl\u0131 yakal\u0131 keten kar\u0131\u015f\u0131ml\u0131 k\u0131sa elbise", "price": "2.099,00 TL"}, {"imgUrl": "https://static.massimodutti.net/3/photos//2023/V/0/1/p/6681/100/669/6681100669_2_5_16.jpg?t=1678968739010&impolicy=massimodutti-itxmediumhigh&imwidth=200&imformat=chrome", "title": "Volanl\u0131 ask\u0131l\u0131 %100 rami elbise", "price": "2.099,00 TL"}, {"imgUrl": "https://static.massimodutti.net/3/photos//2023/V/0/1/p/6655/100/541/6655100541_2_5_16.jpg?t=1678966844232&impolicy=massimodutti-itxmediumhigh&imwidth=200&imformat=chrome", "title": "S\u0131rt\u0131 \u00e7apraz detayl\u0131 midi elbise", "price": "2.099,00 TL"}, {"imgUrl": "https://static.massimodutti.net/3/photos//2023/V/0/1/p/6611/841/500/6611841500_2_9_16.jpg?t=1679646983202&impolicy=massimodutti-itxmediumhigh&imwidth=200&imformat=chrome", "title": "Nokta desenli ask\u0131l\u0131 elbise", "price": "2.099,00 TL"}, {"imgUrl": "https://static.massimodutti.net/3/photos//2023/V/0/1/p/6626/769/800/6626769800_2_9_16.jpg?t=1679646948324&impolicy=massimodutti-itxmediumhigh&imwidth=200&imformat=chrome", "title": "Derin yaka dekolte detayl\u0131 siyah k\u0131sa mini elbise", "price": "1.299,00 TL"}, {"imgUrl": "https://static.massimodutti.net/3/photos//2023/V/0/1/p/6602/674/800/6602674800_2_5_16.jpg?t=1680602168394&impolicy=massimodutti-itxmediumhigh&imwidth=200&imformat=chrome", "title": "D\u00fc\u011fme detayl\u0131 triko elbise", "price": "2.099,00 TL"}, {"imgUrl": "https://static.massimodutti.net/3/photos//2023/V/0/1/p/6656/544/800/11/6656544800_2_6_16.jpg?t=1676903479721&impolicy=massimodutti-itxmediumhigh&imwidth=200&imformat=chrome", "title": "Uzun siyah fitilli V yaka elbise", "price": "1.699,00 TL"}, {"imgUrl": "https://static.massimodutti.net/3/photos//2023/V/0/1/p/6623/650/712/6623650712_2_5_16.jpg?t=1675941865410&impolicy=massimodutti-itxmediumhigh&imwidth=200&imformat=chrome", "title": "Stone print dress", "price": "3.499,00 TL"}, {"imgUrl": "https://static.massimodutti.net/3/photos//2023/V/0/1/p/6630/650/500/6630650500_2_5_16.jpg?t=1675941803639&impolicy=massimodutti-itxmediumhigh&imwidth=200&imformat=chrome", "title": "Uzun pilili elbise", "price": "2.299,00 TL"}, {"imgUrl": "https://static.massimodutti.net/3/photos//2023/V/0/1/p/6633/650/251/6633650251_2_5_16.jpg?t=1675941962182&impolicy=massimodutti-itxmediumhigh&imwidth=200&imformat=chrome", "title": "Fil coup\u00e9 kaftan dress", "price": "2.999,00 TL"}, {"imgUrl": "https://static.massimodutti.net/3/photos//2023/V/0/1/p/9216/952/621/9216952621_2_5_16.jpg?t=1679930606087&impolicy=massimodutti-itxmediumhigh&imwidth=200&imformat=chrome", "title": "T\u00fcy detayl\u0131 uzun elbise - Studio", "price": "3.499,00 TL"}, {"imgUrl": "https://static.massimodutti.net/3/photos//2023/V/0/1/p/9012/962/800/9012962800_2_5_16.jpg?t=1679930256551&impolicy=massimodutti-itxmediumhigh&imwidth=200&imformat=chrome", "title": "Pilili V yaka elbise - Studio", "price": "3.999,00 TL"}, {"imgUrl": "https://static.massimodutti.net/3/photos//2023/V/0/1/p/9221/954/712/9221954712_2_8_16.jpg?t=1679663719903&impolicy=massimodutti-itxmediumhigh&imwidth=200&imformat=chrome", "title": "Kontrast kamisol elbise - Studio", "price": "2.299,00 TL"}, {"imgUrl": "https://static.massimodutti.net/3/photos//2023/V/0/1/p/9221/954/712/03/9221954712_2_7_16.jpg?t=1679663719903&impolicy=massimodutti-itxmediumhigh&imwidth=200&imformat=chrome", "title": "Kontrast kamisol elbise - Studio", "price": "2.299,00 TL"}, {"imgUrl": "https://static.massimodutti.net/3/photos//2023/V/0/1/p/9254/954/700/9254954700_6_1_16.jpg?t=1680512823146&impolicy=massimodutti-itxmediumhigh&imwidth=200&imformat=chrome", "title": "Blazer elbise - Studio", "price": "3.699,00 TL"}, {"imgUrl": "https://static.massimodutti.net/3/photos//2023/V/0/1/p/9220/954/712/9220954712_2_9_16.jpg?t=1679930616325&impolicy=massimodutti-itxmediumhigh&imwidth=200&imformat=chrome", "title": "Pullu elbise - Studio", "price": "3.499,00 TL"}, {"imgUrl": "https://static.massimodutti.net/3/photos//2023/V/0/1/p/9220/954/712/03/9220954712_2_8_16.jpg?t=1679930616325&impolicy=massimodutti-itxmediumhigh&imwidth=200&imformat=chrome", "title": "Pullu elbise - Studio", "price": "3.499,00 TL"}]