[
  {
    "imgUrl": "https://static.massimodutti.net/3/photos//2023/V/0/2/p/0101/499/710/0101499710_2_6_16.jpg?t=1678797856425&impolicy=massimodutti-itxmediumhigh&imwidth=400&imformat=chrome",
    "title": "Cepli regular fit keten g\u00f6mlek - Limited Edition",
    "price": "1.299,00 TL"
  },
  {
    "imgUrl": "https://static.massimodutti.net/3/photos//2023/V/0/2/p/0101/499/710/03/0101499710_2_5_16.jpg?t=1679476391301&impolicy=massimodutti-itxmediumhigh&imwidth=300&imformat=chrome",
    "title": "Cepli regular fit keten g\u00f6mlek - Limited Edition",
    "price": "1.299,00 TL"
  },
  {
    "imgUrl": "https://static.massimodutti.net/3/photos//2023/V/0/2/p/0182/440/800/02/0182440800_2_5_16.jpg?t=1679470517689&impolicy=massimodutti-itxmediumhigh&imwidth=400&imformat=chrome",
    "title": "Cepli %100 keten g\u00f6mlek",
    "price": "1.199,00 TL"
  },
  {
    "imgUrl": "https://static.massimodutti.net/3/photos//2023/V/0/2/p/0182/440/250/0182440250_2_4_16.jpg?t=1677579852112&impolicy=massimodutti-itxmediumhigh&imwidth=400&imformat=chrome",
    "title": "Cepli %100 keten g\u00f6mlek",
    "price": "1.199,00 TL"
  },
  {
    "imgUrl": "https://static.massimodutti.net/3/photos//2023/V/0/2/p/0130/430/524/0130430524_2_7_16.jpg?t=1676364437162&impolicy=massimodutti-itxmediumhigh&imwidth=400&imformat=chrome",
    "title": "%100 keten slim fit g\u00f6mlek",
    "price": "1.199,00 TL"
  },
  {
    "imgUrl": "https://static.massimodutti.net/3/photos//2023/V/0/2/p/0130/430/526/0130430526_2_6_16.jpg?t=1676364437227&impolicy=massimodutti-itxmediumhigh&imwidth=300&imformat=chrome",
    "title": "%100 keten slim fit g\u00f6mlek",
    "price": "1.199,00 TL"
  },
  {
    "imgUrl": "https://static.massimodutti.net/3/photos//2023/V/0/2/p/0130/430/800/0130430800_2_6_16.jpg?t=1676880594019&impolicy=massimodutti-itxmediumhigh&imwidth=400&imformat=chrome",
    "title": "%100 keten slim fit g\u00f6mlek",
    "price": "1.199,00 TL"
  },
  {
    "imgUrl": "https://static.massimodutti.net/3/photos//2023/V/0/2/p/0130/430/390/0130430390_2_4_16.jpg?t=1675847713677&impolicy=massimodutti-itxmediumhigh&imwidth=400&imformat=chrome",
    "title": "%100 keten slim fit g\u00f6mlek",
    "price": "1.199,00 TL"
  },
  {
    "imgUrl": "https://static.massimodutti.net/3/photos//2023/V/0/2/p/0130/430/420/0130430420_2_7_16.jpg?t=1675858897455&impolicy=massimodutti-itxmediumhigh&imwidth=400&imformat=chrome",
    "title": "%100 keten slim fit g\u00f6mlek",
    "price": "1.199,00 TL"
  },
  {
    "imgUrl": "https://static.massimodutti.net/3/photos//2023/V/0/2/p/0130/430/529/0130430529_2_5_16.jpg?t=1675858897576&impolicy=massimodutti-itxmediumhigh&imwidth=300&imformat=chrome",
    "title": "%100 keten slim fit g\u00f6mlek",
    "price": "1.199,00 TL"
  },
  {
    "imgUrl": "https://static.massimodutti.net/3/photos//2023/V/0/2/p/0156/456/401/0156456401_2_6_16.jpg?t=1677580629410&impolicy=massimodutti-itxmediumhigh&imwidth=400&imformat=chrome",
    "title": "Slim fit ince \u00e7izgili pamuk ve keten kar\u0131\u015f\u0131ml\u0131 g\u00f6mlek",
    "price": "1.199,00 TL"
  },
  {
    "imgUrl": "https://static.massimodutti.net/3/photos//2023/V/0/2/p/0157/458/250/0157458250_2_5_16.jpg?t=1677600875669&impolicy=massimodutti-itxmediumhigh&imwidth=300&imformat=chrome",
    "title": "%100 keten regular fit g\u00f6mlek",
    "price": "1.199,00 TL"
  },
  {
    "imgUrl": "https://static.massimodutti.net/3/photos//2023/V/0/2/p/0158/458/719/0158458719_2_5_16.jpg?t=1677664891176&impolicy=massimodutti-itxmediumhigh&imwidth=400&imformat=chrome",
    "title": "Soluk efektli %100 keten g\u00f6mlek",
    "price": "1.199,00 TL"
  },
  {
    "imgUrl": "https://static.massimodutti.net/3/photos//2023/V/0/2/p/0158/458/420/0158458420_2_4_16.jpg?t=1677774738121&impolicy=massimodutti-itxmediumhigh&imwidth=400&imformat=chrome",
    "title": "Soluk efektli %100 keten g\u00f6mlek",
    "price": "1.199,00 TL"
  },
  {
    "imgUrl": "https://static.massimodutti.net/3/photos//2023/V/0/2/p/0165/465/401/0165465401_2_6_16.jpg?t=1676388292403&impolicy=massimodutti-itxmediumhigh&imwidth=400&imformat=chrome",
    "title": "Slim fit \u00e7izgili pamuk ve keten kar\u0131\u015f\u0131ml\u0131 g\u00f6mlek",
    "price": "899,00 TL"
  },
  {
    "imgUrl": "https://static.massimodutti.net/3/photos//2023/V/0/2/p/0169/469/710/0169469710_2_5_16.jpg?t=1678875284174&impolicy=massimodutti-itxmediumhigh&imwidth=300&imformat=chrome",
    "title": "Regular fit ince \u00e7izgili keten g\u00f6mlek",
    "price": "1.199,00 TL"
  },
  {
    "imgUrl": "https://static.massimodutti.net/3/photos//2023/V/0/2/p/0172/472/500/0172472500_2_6_16.jpg?t=1680593926637&impolicy=massimodutti-itxmediumhigh&imwidth=400&imformat=chrome",
    "title": "Regular fit \u00e7izgili %100 keten g\u00f6mlek",
    "price": "1.199,00 TL"
  },
  {
    "imgUrl": "https://static.massimodutti.net/3/photos//2023/V/0/2/p/0168/468/403/0168468403_2_5_16.jpg?t=1680593910816&impolicy=massimodutti-itxmediumhigh&imwidth=300&imformat=chrome",
    "title": "Slim fit \u00e7izgili %100 keten g\u00f6mlek",
    "price": "1.199,00 TL"
  },
  {
    "imgUrl": "https://static.massimodutti.net/3/photos//2023/V/0/2/p/0103/497/403/0103497403_2_5_16.jpg?t=1680593984432&impolicy=massimodutti-itxmediumhigh&imwidth=400&imformat=chrome",
    "title": "Slim fit pamuklu \u00e7izgili Oxford g\u00f6mlek",
    "price": "899,00 TL"
  },
  {
    "imgUrl": "https://static.massimodutti.net/3/photos//2023/V/0/2/p/0113/413/403/0113413403_2_4_16.jpg?t=1667825376568&impolicy=massimodutti-itxmediumhigh&imwidth=300&imformat=chrome",
    "title": "Slim fit pamuklu \u00e7izgili Oxford g\u00f6mlek",
    "price": "899,00 TL"
  },
  {
    "imgUrl": "https://static.massimodutti.net/3/photos//2023/V/0/2/p/0150/450/403/01/0150450403_2_6_16.jpg?t=1679995032297&impolicy=massimodutti-itxmediumhigh&imwidth=400&imformat=chrome",
    "title": "Slim fit pamuklu Oxford g\u00f6mlek",
    "price": "899,00 TL"
  },
  {
    "imgUrl": "https://static.massimodutti.net/3/photos//2023/V/0/2/p/0150/450/250/0150450250_2_4_16.jpg?t=1676978486714&impolicy=massimodutti-itxmediumhigh&imwidth=300&imformat=chrome",
    "title": "Slim fit pamuklu Oxford g\u00f6mlek",
    "price": "899,00 TL"
  },
  {
    "imgUrl": "https://static.massimodutti.net/3/photos//2023/V/0/2/p/0140/440/508/0140440508_2_5_16.jpg?t=1678894646818&impolicy=massimodutti-itxmediumhigh&imwidth=400&imformat=chrome",
    "title": "Slim fit %100 keten h\u00e2kim yaka g\u00f6mlek",
    "price": "1.199,00 TL"
  },
  {
    "imgUrl": "https://static.massimodutti.net/3/photos//2023/V/0/2/p/0140/440/250/01/0140440250_2_4_16.jpg?t=1678883306400&impolicy=massimodutti-itxmediumhigh&imwidth=400&imformat=chrome",
    "title": "Slim fit %100 keten h\u00e2kim yaka g\u00f6mlek",
    "price": "1.199,00 TL"
  },
  {
    "imgUrl": "https://static.massimodutti.net/3/photos//2023/V/0/2/p/0140/440/401/0140440401_2_5_16.jpg?t=1678893130525&impolicy=massimodutti-itxmediumhigh&imwidth=300&imformat=chrome",
    "title": "Slim fit %100 keten h\u00e2kim yaka g\u00f6mlek",
    "price": "1.199,00 TL"
  },
  {
    "imgUrl": "https://static.massimodutti.net/3/photos//2023/V/0/2/p/0185/485/401/0185485401_2_5_16.jpg?t=1679907509757&impolicy=massimodutti-itxmediumhigh&imwidth=400&imformat=chrome",
    "title": "Slim fit pamuklu Oxford g\u00f6mlek",
    "price": "899,00 TL"
  },
  {
    "imgUrl": "https://static.massimodutti.net/3/photos//2023/V/0/2/p/0185/485/250/0185485250_2_4_16.jpg?t=1672921110734&impolicy=massimodutti-itxmediumhigh&imwidth=400&imformat=chrome",
    "title": "Slim fit pamuklu Oxford g\u00f6mlek",
    "price": "899,00 TL"
  },
  {
    "imgUrl": "https://static.massimodutti.net/3/photos//2023/V/0/2/p/0181/481/390/0181481390_2_6_16.jpg?t=1680689831461&impolicy=massimodutti-itxmediumhigh&imwidth=400&imformat=chrome",
    "title": "Slim fit mikro \u00e7izgili pamuklu g\u00f6mlek",
    "price": "899,00 TL"
  },
  {
    "imgUrl": "https://static.massimodutti.net/3/photos//2023/V/0/2/p/0181/481/250/0181481250_2_4_16.jpg?t=1679561079020&impolicy=massimodutti-itxmediumhigh&imwidth=400&imformat=chrome",
    "title": "Slim fit mikro \u00e7izgili pamuklu g\u00f6mlek",
    "price": "899,00 TL"
  },
  {
    "imgUrl": "https://static.massimodutti.net/3/photos//2023/V/0/2/p/0181/481/512/0181481512_2_5_16.jpg?t=1680688911545&impolicy=massimodutti-itxmediumhigh&imwidth=300&imformat=chrome",
    "title": "Slim fit mikro \u00e7izgili pamuklu g\u00f6mlek",
    "price": "899,00 TL"
  },
  {
    "imgUrl": "https://static.massimodutti.net/3/photos//2023/V/0/2/p/0143/443/407/02/0143443407_2_5_16.jpg?t=1677153311967&impolicy=massimodutti-itxmediumhigh&imwidth=400&imformat=chrome",
    "title": "Regular fit %100 pamuklu denim g\u00f6mlek",
    "price": "899,00 TL"
  },
  {
    "imgUrl": "https://static.massimodutti.net/3/photos//2023/V/0/2/p/0145/445/406/0145445406_2_4_16.jpg?t=1675165202906&impolicy=massimodutti-itxmediumhigh&imwidth=200&imformat=chrome",
    "title": "Regular fit %100 pamuklu denim g\u00f6mlek",
    "price": "899,00 TL"
  },
  {
    "imgUrl": "https://static.massimodutti.net/3/photos//2023/V/0/2/p/0163/463/710/0163463710_2_7_16.jpg?t=1676374605521&impolicy=massimodutti-itxmediumhigh&imwidth=400&imformat=chrome",
    "title": "Slim fit \u00e7izgili pamuk ve keten kar\u0131\u015f\u0131ml\u0131 g\u00f6mlek",
    "price": "899,00 TL"
  },
  {
    "imgUrl": "https://static.massimodutti.net/3/photos//2023/V/0/2/p/0167/467/401/0167467401_2_5_16.jpg?t=1680593921550&impolicy=massimodutti-itxmediumhigh&imwidth=300&imformat=chrome",
    "title": "Regular fit kal\u0131n \u00e7izgili %100 keten g\u00f6mlek",
    "price": "1.199,00 TL"
  },
  {
    "imgUrl": "https://static.massimodutti.net/3/photos//2023/V/0/2/p/0162/462/403/0162462403_2_5_16.jpg?t=1676371515020&impolicy=massimodutti-itxmediumhigh&imwidth=300&imformat=chrome",
    "title": "Slim fit kazaya\u011f\u0131 desenli keten kar\u0131\u015f\u0131ml\u0131 g\u00f6mlek",
    "price": "899,00 TL"
  },
  {
    "imgUrl": "https://static.massimodutti.net/3/photos//2023/V/0/2/p/0155/455/403/0155455403_2_5_16.jpg?t=1679907495811&impolicy=massimodutti-itxmediumhigh&imwidth=300&imformat=chrome",
    "title": "Regular fit boyal\u0131 keten g\u00f6mlek",
    "price": "1.199,00 TL"
  },
  {
    "imgUrl": "https://static.massimodutti.net/3/photos//2023/V/0/2/p/0153/453/403/0153453403_2_8_16.jpg?t=1679907503861&impolicy=massimodutti-itxmediumhigh&imwidth=400&imformat=chrome",
    "title": "Slim fit ince \u00e7izgili flaml\u0131 pamuklu g\u00f6mlek",
    "price": "899,00 TL"
  },
  {
    "imgUrl": "https://static.massimodutti.net/3/photos//2023/V/0/2/p/0186/486/401/0186486401_2_4_16.jpg?t=1675079983669&impolicy=massimodutti-itxmediumhigh&imwidth=400&imformat=chrome",
    "title": "\u00c7izgili pamuklu slim fit g\u00f6mlek",
    "price": "899,00 TL"
  },
  {
    "imgUrl": "https://static.massimodutti.net/3/photos//2023/V/0/2/p/0149/449/403/0149449403_2_5_16.jpg?t=1679991464829&impolicy=massimodutti-itxmediumhigh&imwidth=300&imformat=chrome",
    "title": "Slim fit mikro \u00e7izgili poplin pamuklu g\u00f6mlek",
    "price": "899,00 TL"
  },
  {
    "imgUrl": "https://static.massimodutti.net/3/photos//2023/V/0/2/p/0147/447/401/0147447401_2_6_16.jpg?t=1672748978334&impolicy=massimodutti-itxmediumhigh&imwidth=400&imformat=chrome",
    "title": "Slim fit dokulu pamuklu g\u00f6mlek",
    "price": "899,00 TL"
  },
  {
    "imgUrl": "https://static.massimodutti.net/3/photos//2023/V/0/2/p/0147/447/250/01/0147447250_2_4_16.jpg?t=1672299631922&impolicy=massimodutti-itxmediumhigh&imwidth=400&imformat=chrome",
    "title": "Slim fit dokulu pamuklu g\u00f6mlek",
    "price": "899,00 TL"
  },
  {
    "imgUrl": "https://static.massimodutti.net/3/photos//2023/V/0/2/p/0147/447/500/0147447500_2_5_16.jpg?t=1672748978400&impolicy=massimodutti-itxmediumhigh&imwidth=300&imformat=chrome",
    "title": "Slim fit dokulu pamuklu g\u00f6mlek",
    "price": "899,00 TL"
  },
  {
    "imgUrl": "https://static.massimodutti.net/3/photos//2023/V/0/2/p/0134/434/250/0134434250_2_8_16.jpg?t=1673959450753&impolicy=massimodutti-itxmediumhigh&imwidth=400&imformat=chrome",
    "title": "Slim fit dokulu pamuklu g\u00f6mlek",
    "price": "899,00 TL"
  },
  {
    "imgUrl": "https://static.massimodutti.net/3/photos//2023/V/0/2/p/0122/422/403/0122422403_2_5_16.jpg?t=1675348847082&impolicy=massimodutti-itxmediumhigh&imwidth=300&imformat=chrome",
    "title": "Slim fit pamuklu melanj g\u00f6mlek",
    "price": "899,00 TL"
  },
  {
    "imgUrl": "https://static.massimodutti.net/3/photos//2023/V/0/2/p/0136/436/250/0136436250_2_5_16.jpg?t=1671024979569&impolicy=massimodutti-itxmediumhigh&imwidth=400&imformat=chrome",
    "title": "Slim fit dokulu pamuklu g\u00f6mlek",
    "price": "899,00 TL"
  },
  {
    "imgUrl": "https://static.massimodutti.net/3/photos//2023/V/0/2/p/0180/440/250/0180440250_2_6_16.jpg?t=1676880385354&impolicy=massimodutti-itxmediumhigh&imwidth=400&imformat=chrome",
    "title": "Slim fit hakim yaka poplin g\u00f6mlek",
    "price": "899,00 TL"
  },
  {
    "imgUrl": "https://static.massimodutti.net/3/photos//2023/V/0/2/p/0180/440/250/01/0180440250_2_4_16.jpg?t=1679925691593&impolicy=massimodutti-itxmediumhigh&imwidth=400&imformat=chrome",
    "title": "Slim fit hakim yaka poplin g\u00f6mlek",
    "price": "899,00 TL"
  },
  {
    "imgUrl": "https://static.massimodutti.net/3/photos//2023/V/0/2/p/0180/440/402/0180440402_2_5_16.jpg?t=1676880385425&impolicy=massimodutti-itxmediumhigh&imwidth=400&imformat=chrome",
    "title": "Slim fit hakim yaka poplin g\u00f6mlek",
    "price": "899,00 TL"
  },
  {
    "imgUrl": "https://static.massimodutti.net/3/photos//2023/V/0/2/p/0139/439/401/0139439401_2_9_16.jpg?t=1673884562195&impolicy=massimodutti-itxmediumhigh&imwidth=400&imformat=chrome",
    "title": "Regular fit \u00e7ift \u00e7izgili g\u00f6mlek",
    "price": "899,00 TL"
  },
  {
    "imgUrl": "https://static.massimodutti.net/3/photos//2023/V/0/2/p/0184/484/401/0184484401_2_4_16.jpg?t=1675158553614&impolicy=massimodutti-itxmediumhigh&imwidth=500&imformat=chrome",
    "title": "Slim fit \u00e7izgili poplin pamuklu g\u00f6mlek",
    "price": "899,00 TL"
  },
  {
    "imgUrl": "https://static.massimodutti.net/3/photos//2023/V/0/2/p/0114/414/403/0114414403_2_5_16.jpg?t=1669305147055&impolicy=massimodutti-itxmediumhigh&imwidth=400&imformat=chrome",
    "title": "\u00c7izgili pamuklu slim fit g\u00f6mlek",
    "price": "899,00 TL"
  },
  {
    "imgUrl": "https://static.massimodutti.net/3/photos//2023/V/0/2/p/0152/452/403/0152452403_2_5_16.jpg?t=1679991449900&impolicy=massimodutti-itxmediumhigh&imwidth=400&imformat=chrome",
    "title": "Slim fit ince \u00e7izgili pamuklu g\u00f6mlek",
    "price": "899,00 TL"
  },
  {
    "imgUrl": "https://static.massimodutti.net/3/photos//2023/V/0/2/p/0152/452/403/02/0152452403_2_4_16.jpg?t=1676453707239&impolicy=massimodutti-itxmediumhigh&imwidth=400&imformat=chrome",
    "title": "Slim fit ince \u00e7izgili pamuklu g\u00f6mlek",
    "price": "899,00 TL"
  },
  {
    "imgUrl": "https://static.massimodutti.net/3/photos//2023/V/0/2/p/0106/406/401/02/0106406401_7_1_16.jpg?t=1677164464090&impolicy=massimodutti-itxmediumhigh&imwidth=700&imformat=chrome",
    "title": "Soluk efektli regular fit pamuklu denim g\u00f6mlek",
    "price": "1.199,00 TL"
  },
  {
    "imgUrl": "https://static.massimodutti.net/3/photos//2023/V/0/2/p/0106/406/500/0106406500_2_4_16.jpg?t=1672921110338&impolicy=massimodutti-itxmediumhigh&imwidth=400&imformat=chrome",
    "title": "Soluk efektli regular fit pamuklu denim g\u00f6mlek",
    "price": "1.199,00 TL"
  },
  {
    "imgUrl": "https://static.massimodutti.net/3/photos//2023/V/0/2/p/0146/446/406/0146446406_2_6_16.jpg?t=1676364346475&impolicy=massimodutti-itxmediumhigh&imwidth=300&imformat=chrome",
    "title": "Regular fit %100 pamuklu denim g\u00f6mlek",
    "price": "1.199,00 TL"
  },
  {
    "imgUrl": "https://static.massimodutti.net/3/photos//2023/V/0/2/p/0100/398/250/0100398250_2_6_16.jpg?t=1676473157466&impolicy=massimodutti-itxmediumhigh&imwidth=400&imformat=chrome",
    "title": "Petek dokulu slim fit g\u00f6mlek",
    "price": "899,00 TL"
  },
  {
    "imgUrl": "https://static.massimodutti.net/3/photos//2023/V/0/2/p/0166/466/390/0166466390_2_5_16.jpg?t=1676388273852&impolicy=massimodutti-itxmediumhigh&imwidth=300&imformat=chrome",
    "title": "Slim fit \u00e7izgili pamuk ve keten kar\u0131\u015f\u0131ml\u0131 g\u00f6mlek",
    "price": "899,00 TL"
  },
  {
    "imgUrl": "https://static.massimodutti.net/3/photos//2023/V/0/2/p/0741/277/800/01/0741277800_2_6_16.jpg?t=1678101643402&impolicy=massimodutti-itxmediumhigh&imwidth=400&imformat=chrome",
    "title": "K\u0131sa kollu keten ve pamuk kar\u0131\u015f\u0131ml\u0131 g\u00f6mlek",
    "price": "899,00 TL"
  },
  {
    "imgUrl": "https://static.massimodutti.net/3/photos//2023/V/0/2/p/0741/277/507/0741277507_2_5_16.jpg?t=1678877890636&impolicy=massimodutti-itxmediumhigh&imwidth=300&imformat=chrome",
    "title": "K\u0131sa kollu keten ve pamuk kar\u0131\u015f\u0131ml\u0131 g\u00f6mlek",
    "price": "899,00 TL"
  },
  {
    "imgUrl": "https://static.massimodutti.net/3/photos//2023/V/0/2/p/0137/438/406/0137438406_2_6_16.jpg?t=1674743877782&impolicy=massimodutti-itxmediumhigh&imwidth=400&imformat=chrome",
    "title": "Slim fit pamuklu poplin g\u00f6mlek",
    "price": "899,00 TL"
  },
  {
    "imgUrl": "https://static.massimodutti.net/3/photos//2023/V/0/2/p/0137/438/406/01/0137438406_2_5_16.jpg?t=1674743877782&impolicy=massimodutti-itxmediumhigh&imwidth=500&imformat=chrome",
    "title": "Slim fit pamuklu poplin g\u00f6mlek",
    "price": "899,00 TL"
  },
  {
    "imgUrl": "https://static.massimodutti.net/3/photos//2023/V/0/2/p/0137/438/250/0137438250_2_5_16.jpg?t=1674743877496&impolicy=massimodutti-itxmediumhigh&imwidth=400&imformat=chrome",
    "title": "Slim fit pamuklu poplin g\u00f6mlek",
    "price": "899,00 TL"
  },
  {
    "imgUrl": "https://static.massimodutti.net/3/photos//2023/V/0/2/p/0132/432/250/0132432250_2_5_16.jpg?t=1668090200932&impolicy=massimodutti-itxmediumhigh&imwidth=400&imformat=chrome",
    "title": "Regular fit dokulu mikro kareli g\u00f6mlek",
    "price": "899,00 TL"
  },
  {
    "imgUrl": "https://static.massimodutti.net/3/photos//2023/V/0/2/p/0132/432/250/01/0132432250_2_4_16.jpg?t=1668499348534&impolicy=massimodutti-itxmediumhigh&imwidth=400&imformat=chrome",
    "title": "Regular fit dokulu mikro kareli g\u00f6mlek",
    "price": "899,00 TL"
  },
  {
    "imgUrl": "https://static.massimodutti.net/3/photos//2023/V/0/2/p/0158/368/401/0158368401_2_5_16.jpg?t=1680593977606&impolicy=massimodutti-itxmediumhigh&imwidth=400&imformat=chrome",
    "title": "Slim fit pamuklu poplin g\u00f6mlek",
    "price": "899,00 TL"
  },
  {
    "imgUrl": "https://static.massimodutti.net/3/photos//2023/V/0/2/p/0181/440/403/0181440403_2_7_16.jpg?t=1676880408049&impolicy=massimodutti-itxmediumhigh&imwidth=300&imformat=chrome",
    "title": "Slim fit \u00e7izgili hakim yaka poplin g\u00f6mlek",
    "price": "899,00 TL"
  },
  {
    "imgUrl": "https://static.massimodutti.net/3/photos//2023/V/0/2/p/0122/340/250/01/0122340250_2_6_16.jpg?t=1673858419842&impolicy=massimodutti-itxmediumhigh&imwidth=400&imformat=chrome",
    "title": "STRETCH FIT D\u00dcZ RENKL\u0130 PAMUKLU G\u00d6MLEK",
    "price": "1.199,00 TL"
  },
  {
    "imgUrl": "https://static.massimodutti.net/3/photos//2023/V/0/2/p/0122/340/250/0122340250_2_4_16.jpg?t=1657616425953&impolicy=massimodutti-itxmediumhigh&imwidth=400&imformat=chrome",
    "title": "STRETCH FIT D\u00dcZ RENKL\u0130 PAMUKLU G\u00d6MLEK",
    "price": "1.199,00 TL"
  },
  {
    "imgUrl": "https://static.massimodutti.net/3/photos//2023/V/0/2/p/0101/150/403/0101150403_2_5_16.jpg?t=1674045788323&impolicy=massimodutti-itxmediumhigh&imwidth=300&imformat=chrome",
    "title": "Regular fit \u00e7izgili easy iron g\u00f6mlek",
    "price": "1.199,00 TL"
  },
  {
    "imgUrl": "https://static.massimodutti.net/3/photos//2023/V/0/2/p/0110/160/401/0110160401_2_6_16.jpg?t=1678204749902&impolicy=massimodutti-itxmediumhigh&imwidth=400&imformat=chrome",
    "title": "%100 keten slim fit g\u00f6mlek",
    "price": "1.299,00 TL"
  },
  {
    "imgUrl": "https://static.massimodutti.net/3/photos//2023/V/0/2/p/0110/160/250/0110160250_2_4_16.jpg?t=1677663536127&impolicy=massimodutti-itxmediumhigh&imwidth=400&imformat=chrome",
    "title": "%100 keten slim fit g\u00f6mlek",
    "price": "1.299,00 TL"
  },
  {
    "imgUrl": "https://static.massimodutti.net/3/photos//2023/V/0/2/p/0104/153/250/0104153250_2_5_16.jpg?t=1673606125514&impolicy=massimodutti-itxmediumhigh&imwidth=300&imformat=chrome",
    "title": "Slim fit \u00e7izgili stre\u00e7 g\u00f6mlek",
    "price": "1.199,00 TL"
  },
  {
    "imgUrl": "https://static.massimodutti.net/3/photos//2023/V/0/2/p/0103/152/802/0103152802_2_6_16.jpg?t=1676370557670&impolicy=massimodutti-itxmediumhigh&imwidth=400&imformat=chrome",
    "title": "Slim fit \u00e7izgili easy iron melanj g\u00f6mlek",
    "price": "1.199,00 TL"
  },
  {
    "imgUrl": "https://static.massimodutti.net/3/photos//2023/V/0/2/p/0111/161/403/0111161403_2_5_16.jpg?t=1673859631002&impolicy=massimodutti-itxmediumhigh&imwidth=300&imformat=chrome",
    "title": "\u00c7izgili pamuklu slim fit g\u00f6mlek",
    "price": "1.199,00 TL"
  },
  {
    "imgUrl": "https://static.massimodutti.net/3/photos//2023/V/0/2/p/0134/390/406/0134390406_2_6_16.jpg?t=1675070606518&impolicy=massimodutti-itxmediumhigh&imwidth=400&imformat=chrome",
    "title": "Easy iron slim fit \u00e7izgili g\u00f6mlek",
    "price": "1.199,00 TL"
  },
  {
    "imgUrl": "https://static.massimodutti.net/3/photos//2023/V/0/2/p/0188/361/250/0188361250_2_5_16.jpg?t=1675071354690&impolicy=massimodutti-itxmediumhigh&imwidth=300&imformat=chrome",
    "title": "\u00c7ift man\u015fetli regular fit g\u00f6mlek",
    "price": "1.299,00 TL"
  },
  {
    "imgUrl": "https://static.massimodutti.net/3/photos//2023/V/0/2/p/0136/360/250/0136360250_2_6_16.jpg?t=1675070594834&impolicy=massimodutti-itxmediumhigh&imwidth=400&imformat=chrome",
    "title": "Easy iron slim fit dokulu \u00e7izgili g\u00f6mlek",
    "price": "1.199,00 TL"
  },
  {
    "imgUrl": "https://static.massimodutti.net/3/photos//2023/V/0/2/p/0140/640/250/0140640250_2_3_16.jpg?t=1643270592368&impolicy=massimodutti-itxmediumhigh&imwidth=200&imformat=chrome",
    "title": "Pamuklu bal\u0131ks\u0131rt\u0131 regular fit g\u00f6mlek",
    "price": "1.199,00 TL"
  },
  {
    "imgUrl": "https://static.massimodutti.net/3/photos//2023/V/0/2/p/0184/342/250/0184342250_2_6_16.jpg?t=1675071296706&impolicy=massimodutti-itxmediumhigh&imwidth=400&imformat=chrome",
    "title": "Slim fit pamuklu poplin g\u00f6mlek",
    "price": "1.199,00 TL"
  },
  {
    "imgUrl": "https://static.massimodutti.net/3/photos//2023/V/0/2/p/0130/361/250/0130361250_2_4_16.jpg?t=1662388275985&impolicy=massimodutti-itxmediumhigh&imwidth=400&imformat=chrome",
    "title": "Regular fit pamuklu poplin g\u00f6mlek",
    "price": "1.299,00 TL"
  },
  {
    "imgUrl": "https://static.massimodutti.net/3/photos//2023/V/0/2/p/0126/650/250/0126650250_2_5_16.jpg?t=1675072033946&impolicy=massimodutti-itxmediumhigh&imwidth=300&imformat=chrome",
    "title": "Dokulu slim fit stre\u00e7 g\u00f6mlek",
    "price": "1.199,00 TL"
  },
  {
    "imgUrl": "https://static.massimodutti.net/3/photos//2023/V/0/2/p/0108/157/403/0108157403_2_6_16.jpg?t=1675069574500&impolicy=massimodutti-itxmediumhigh&imwidth=400&imformat=chrome",
    "title": "Easy iron slim fit dokulu g\u00f6mlek",
    "price": "1.199,00 TL"
  },
  {
    "imgUrl": "https://static.massimodutti.net/3/photos//2023/V/0/2/p/0102/151/250/0102151250_2_4_16.jpg?t=1674723522175&impolicy=massimodutti-itxmediumhigh&imwidth=300&imformat=chrome",
    "title": "Slim fit pamuklu triko g\u00f6mlek",
    "price": "1.199,00 TL"
  },
  {
    "imgUrl": "https://static.massimodutti.net/3/photos//2023/V/0/2/p/0184/684/403/0184684403_2_5_16.jpg?t=1675066984035&impolicy=massimodutti-itxmediumhigh&imwidth=300&imformat=chrome",
    "title": "Easy iron slim fit serj g\u00f6mlek",
    "price": "1.699,00 TL"
  },
  {
    "imgUrl": "https://static.massimodutti.net/3/photos//2023/V/0/2/p/0185/685/403/0185685403_2_5_16.jpg?t=1675066975385&impolicy=massimodutti-itxmediumhigh&imwidth=300&imformat=chrome",
    "title": "Easy iron slim fit \u00e7izgili g\u00f6mlek",
    "price": "1.699,00 TL"
  },
  {
    "imgUrl": "https://static.massimodutti.net/3/photos//2023/V/0/2/p/0180/680/250/0180680250_2_5_16.jpg?t=1675066940549&impolicy=massimodutti-itxmediumhigh&imwidth=300&imformat=chrome",
    "title": "Easy iron slim fit dokulu g\u00f6mlek",
    "price": "1.699,00 TL"
  },
  {
    "imgUrl": "https://static.massimodutti.net/3/photos//2023/V/0/2/p/0182/682/250/0182682250_2_6_16.jpg?t=1678182455733&impolicy=massimodutti-itxmediumhigh&imwidth=300&imformat=chrome",
    "title": "Easy iron slim fit \u00e7izgili dokulu g\u00f6mlek",
    "price": "1.699,00 TL"
  },
  {
    "imgUrl": "https://static.massimodutti.net/3/photos//2023/V/0/2/p/0131/728/829/0131728829_2_5_16.jpg?t=1674589572156&impolicy=massimodutti-itxmediumhigh&imwidth=400&imformat=chrome",
    "title": "Rahat kesim pamuklu g\u00f6mlek - Studio",
    "price": "1.299,00 TL"
  },
  {
    "imgUrl": "https://static.massimodutti.net/3/photos//2023/V/0/2/p/0131/728/482/0131728482_2_5_16.jpg?t=1674575013451&impolicy=massimodutti-itxmediumhigh&imwidth=300&imformat=chrome",
    "title": "Rahat kesim pamuklu g\u00f6mlek - Studio",
    "price": "1.299,00 TL"
  },
  {
    "imgUrl": "https://static.massimodutti.net/3/photos//2023/V/0/2/p/0131/728/520/0131728520_2_5_16.jpg?t=1674575724765&impolicy=massimodutti-itxmediumhigh&imwidth=300&imformat=chrome",
    "title": "Rahat kesim pamuklu g\u00f6mlek - Studio",
    "price": "1.299,00 TL"
  },
  {
    "imgUrl": "https://static.massimodutti.net/3/photos//2023/V/0/2/p/0130/728/700/0130728700_2_5_16.jpg?t=1674575973231&impolicy=massimodutti-itxmediumhigh&imwidth=400&imformat=chrome",
    "title": "Slim fit esnek g\u00f6mlek - Studio",
    "price": "1.299,00 TL"
  },
  {
    "imgUrl": "https://static.massimodutti.net/3/photos//2023/V/0/2/p/0130/728/250/0130728250_2_9_16.jpg?t=1674574337543&impolicy=massimodutti-itxmediumhigh&imwidth=300&imformat=chrome",
    "title": "Slim fit esnek g\u00f6mlek - Studio",
    "price": "1.299,00 TL"
  },
  {
    "imgUrl": "https://static.massimodutti.net/3/photos//2023/V/0/2/p/0130/728/804/0130728804_2_8_16.jpg?t=1674575973332&impolicy=massimodutti-itxmediumhigh&imwidth=300&imformat=chrome",
    "title": "Slim fit esnek g\u00f6mlek - Studio",
    "price": "1.299,00 TL"
  }
]
