[{"imgUrl": "https://dfcdn.defacto.com.tr/304/N0503AZ_23SP_BK27_04_02.jpg", "title": "Slim Fit Dokulu Blazer Ceket", "price": "699,99\nTL"}, {"imgUrl": "https://dfcdn.defacto.com.tr/304/Z3316AZ_23SP_NV64_04_02.jpg", "title": "Slim Fit Astarl\u0131 Blazer", "price": "1299,99\nTL"}, {"imgUrl": "https://dfcdn.defacto.com.tr/304/N0503AZ_22AU_AR102_02_02.jpg", "title": "Slim Fit Dokulu Blazer Ceket", "price": "699,99\nTL"}, {"imgUrl": "https://dfcdn.defacto.com.tr/304/W9254AZ_23SP_BK27_04_05.jpg", "title": "Slim Fit Astarl\u0131 Blazer", "price": "999,99\nTL"}, {"imgUrl": "https://dfcdn.defacto.com.tr/304/Y7473AZ_23SP_KH64_04_01.jpg", "title": "Slim Fit Astarl\u0131 Blazer", "price": "699,99\nTL"}, {"imgUrl": "https://dfcdn.defacto.com.tr/304/X4857AZ_22SM_IN95_04_02.jpg", "title": "Slim Fit Basic Blazer Ceket", "price": "999,99\nTL"}, {"imgUrl": "https://dfcdn.defacto.com.tr/304/W9254AZ_22SP_NV64_02_01.jpg", "title": "Slim Fit Astarl\u0131 Blazer", "price": "999,99\nTL"}, {"imgUrl": "https://dfcdn.defacto.com.tr/304/Y9991AZ_22SM_BG260_04_01.jpg", "title": "Slim Fit Astarl\u0131 Blazer", "price": "999,99\nTL"}, {"imgUrl": "https://dfcdn.defacto.com.tr/376/N0503AZ_22AU_NV64_02_03.jpg", "title": "Slim Fit Dokulu Blazer Ceket", "price": "699,99\nTL"}, {"imgUrl": "https://dfcdn.defacto.com.tr/376/X4905AZ_22SM_BG176_04_02.jpg", "title": "Modern Fit Keten G\u00f6r\u00fcn\u00fcml\u00fc Blazer Ceket", "price": "699,99\nTL"}, {"imgUrl": "https://dfcdn.defacto.com.tr/376/N0503AZ_22SP_GR210_01_02.jpg", "title": "Slim Fit Dokulu Blazer Ceket", "price": "699,99\nTL"}, {"imgUrl": "https://dfcdn.defacto.com.tr/376/X4905AZ_22SM_GR158_04_01.jpg", "title": "Modern Fit Keten G\u00f6r\u00fcn\u00fcml\u00fc Blazer Ceket", "price": "499,99\nTL"}, {"imgUrl": "https://dfcdn.defacto.com.tr/304/W9254AZ_23SP_BG731_04_03.jpg", "title": "Slim Fit Astarl\u0131 Blazer", "price": "999,99\nTL"}, {"imgUrl": "https://dfcdn.defacto.com.tr/304/X4844AZ_22SM_BN132_04_01.jpg", "title": "Slim Fit Yar\u0131m Astar Blazer", "price": "999,99\nTL"}, {"imgUrl": "https://dfcdn.defacto.com.tr/304/Y9991AZ_22SM_TR322_04_01.jpg", "title": "Slim Fit Astarl\u0131 Blazer", "price": "999,99\nTL"}, {"imgUrl": "https://dfcdn.defacto.com.tr/304/V0545AZ_21SM_NV64_04_02.jpg", "title": "Modern Fit Blazer Ceket", "price": "999,99\nTL"}, {"imgUrl": "https://dfcdn.defacto.com.tr/304/W9254AZ_23SP_GR221_02_03.jpg", "title": "Slim Fit Astarl\u0131 Blazer", "price": "999,99\nTL"}, {"imgUrl": "https://dfcdn.defacto.com.tr/304/Y7677AZ_22SM_BN132_04_01.jpg", "title": "Slim Fit Astarl\u0131 Blazer", "price": "999,99\nTL"}, {"imgUrl": "https://dfcdn.defacto.com.tr/304/X4898AZ_22SM_IN75_04_01.jpg", "title": "Slim Fit Keten Kar\u0131\u015f\u0131ml\u0131 Blazer Ceket", "price": "799,99\nTL"}, {"imgUrl": "https://dfcdn.defacto.com.tr/304/X5079AZ_22SM_BG193_04_03.jpg", "title": "Relax Fit Polo Yaka Twill Blazer", "price": "999,99\nTL"}, {"imgUrl": "https://dfcdn.defacto.com.tr/376/Z3318AZ_22WN_BG73_04_01.jpg", "title": "Slim Fit Astarl\u0131 \u00c7izgili Blazer", "price": "1299,99\nTL"}, {"imgUrl": "https://dfcdn.defacto.com.tr/376/Y7676AZ_22SM_GN469_04_01.jpg", "title": "Slim Fit Astarl\u0131 Blazer", "price": "999,99\nTL"}, {"imgUrl": "https://dfcdn.defacto.com.tr/376/X4844AZ_22SM_GR210_04_01.jpg", "title": "Slim Fit Yar\u0131m Astar Blazer", "price": "999,99\nTL"}, {"imgUrl": "https://dfcdn.defacto.com.tr/376/X4898AZ_22SM_BG49_04_01.jpg", "title": "Slim Fit Keten Kar\u0131\u015f\u0131ml\u0131 Blazer Ceket", "price": "799,99\nTL"}, {"imgUrl": "https://dfcdn.defacto.com.tr/304/X4829AZ_22SM_GR210_04_01.jpg", "title": "Slim Fit Yar\u0131m Astar Blazer Ceket", "price": "999,99\nTL"}, {"imgUrl": "https://dfcdn.defacto.com.tr/304/V5499AZ_22SP_BG49_04_03.jpg", "title": "Slim Fit Yar\u0131m Astar Blazer", "price": "799,99\nTL"}, {"imgUrl": "https://dfcdn.defacto.com.tr/304/V5499AZ_22SP_BN132_04_01.jpg", "title": "Slim Fit Yar\u0131m Astar Blazer", "price": "499,99\nTL"}, {"imgUrl": "https://dfcdn.defacto.com.tr/304/Y6725AZ_22SM_GR210_04_01.jpg", "title": "Slim Fit Astarl\u0131 Blazer Ceket", "price": "599,99\nTL"}, {"imgUrl": "https://dfcdn.defacto.com.tr/304/Y9983AZ_22WN_BE415_04_01.jpg", "title": "Slim Fit Astarl\u0131 Blazer", "price": "599,99\nTL"}, {"imgUrl": "https://dfcdn.defacto.com.tr/304/X4977AZ_23SM_BG193_04_01.jpg", "title": "Slim Fit Astarl\u0131 Blazer", "price": "799,99\nTL"}]