[{"imgUrl": "https://dfcdn.defacto.com.tr/304/U3655AZ_NS_GR4_04_03.jpg", "title": "Erkek Laptop B\u00f6lmeli Okul S\u0131rt \u00c7antas\u0131", "price": "299,99\nTL"}, {"imgUrl": "https://dfcdn.defacto.com.tr/304/W9934AZ_NS_BK27_04_02.jpg", "title": "Erkek Yaz\u0131 Bask\u0131l\u0131 B\u00fcy\u00fck Okul S\u0131rt \u00c7antas\u0131", "price": "149,99\nTL"}, {"imgUrl": "https://dfcdn.defacto.com.tr/304/A2812AX_NS_BK27_04_01.jpg", "title": "Erkek Defacto Fit NBA Chicago Bulls S\u0131rt \u00c7antas\u0131", "price": "399,99\nTL"}, {"imgUrl": "https://dfcdn.defacto.com.tr/304/U3650AZ_NS_GR2_04_01.jpg", "title": "Erkek Ekstra G\u00f6zl\u00fc Ultra Hafif Bel \u00c7antas\u0131", "price": "149,99\nTL"}, {"imgUrl": "https://dfcdn.defacto.com.tr/304/U3655AZ_NS_BE2_04_03.jpg", "title": "Erkek Laptop B\u00f6lmeli Okul S\u0131rt \u00c7antas\u0131", "price": "299,99\nTL"}, {"imgUrl": "https://dfcdn.defacto.com.tr/304/V1466AZ_NS_BK27_04_01.jpg", "title": "Erkek Laptop B\u00f6lmeli B\u00fcy\u00fck Okul S\u0131rt \u00c7antas\u0131", "price": "299,99\nTL"}, {"imgUrl": "https://dfcdn.defacto.com.tr/304/A2819AX_NS_BG26_04_01.jpg", "title": "Erkek Defacto Fit NBA Milwaukee Bucks S\u0131rt \u00c7antas\u0131", "price": "399,99\nTL"}, {"imgUrl": "https://dfcdn.defacto.com.tr/304/V1466AZ_NS_GR4_04_01.jpg", "title": "Erkek Laptop B\u00f6lmeli B\u00fcy\u00fck Okul S\u0131rt \u00c7antas\u0131", "price": "299,99\nTL"}, {"imgUrl": "https://dfcdn.defacto.com.tr/376/A2815AX_NS_BK27_04_01.jpg", "title": "Erkek Defacto Fit NBA Los Angeles Lakers S\u0131rt \u00c7antas\u0131", "price": "399,99\nTL"}, {"imgUrl": "https://dfcdn.defacto.com.tr/376/V1478AZ_NS_BN45_04_02.jpg", "title": "Erkek B\u00fcy\u00fck Suni Deri S\u0131rt \u00c7antas\u0131", "price": "299,99\nTL"}, {"imgUrl": "https://dfcdn.defacto.com.tr/376/Z1022AZ_NS_BK27_04_01.jpg", "title": "Erkek Suni Deri \u00c7apraz \u00c7anta", "price": "199,99\nTL"}, {"imgUrl": "https://dfcdn.defacto.com.tr/376/A1034AX_NS_GR4_04_01.jpg", "title": "Erkek Su \u0130tici Kuma\u015f S\u0131rt \u00c7antas\u0131", "price": "399,99\nTL"}, {"imgUrl": "https://dfcdn.defacto.com.tr/304/V1478AZ_NS_BK27_04_01.jpg", "title": "Erkek B\u00fcy\u00fck Suni Deri S\u0131rt \u00c7antas\u0131", "price": "299,99\nTL"}, {"imgUrl": "https://dfcdn.defacto.com.tr/304/Y1374AZ_NS_BK27_04_01.jpg", "title": "Erkek Kendi Kendini Onaran Su Tutmayan Kuma\u015f S\u0131rt \u00c7antas\u0131", "price": "349,99\nTL"}, {"imgUrl": "https://dfcdn.defacto.com.tr/304/U3645AZ_NS_NV2_04_01.jpg", "title": "Erkek \u00c7apraz \u00c7anta", "price": "149,99\nTL"}, {"imgUrl": "https://dfcdn.defacto.com.tr/304/Y1379AZ_NS_OG37_04_02.jpg", "title": "Erkek Kendi Kendini Onaran Su Tutmayan Kuma\u015f S\u0131rt \u00c7antas\u0131", "price": "299,99\nTL"}, {"imgUrl": "https://dfcdn.defacto.com.tr/304/A2370AX_NS_BK27_04_02.jpg", "title": "Erkek Suni Deri Tablet \u00c7antas\u0131", "price": "249,99\nTL"}, {"imgUrl": "https://dfcdn.defacto.com.tr/304/A2448AX_NS_BK27_04_01.jpg", "title": "Erkek Defacto Fit Kendi Kendini Onaran Su Tutmayan Kuma\u015f S\u0131rt \u00c7antas\u0131", "price": "349,99\nTL"}, {"imgUrl": "https://dfcdn.defacto.com.tr/304/U3655AZ_NS_YL1_04_03.jpg", "title": "Erkek Laptop B\u00f6lmeli Okul S\u0131rt \u00c7antas\u0131", "price": "299,99\nTL"}, {"imgUrl": "https://dfcdn.defacto.com.tr/304/Y1365AZ_NS_BK27_04_02.jpg", "title": "Erkek Kendi Kendini Onaran Su Tutmayan Kuma\u015f S\u0131rt \u00c7antas\u0131", "price": "199,99\nTL"}, {"imgUrl": "https://dfcdn.defacto.com.tr/376/S5667AZ_NS_BK27_04_02.jpg", "title": "Erkek \u00c7apraz Omuz \u00c7antas\u0131", "price": "149,99\nTL"}, {"imgUrl": "https://dfcdn.defacto.com.tr/376/Z8043AZ_NS_KR1_04_02.jpg", "title": "Erkek F\u0131rat S\u0131rt \u00c7antas\u0131", "price": "299,99\nTL"}, {"imgUrl": "https://dfcdn.defacto.com.tr/376/W9934AZ_NS_GR2_04_03.jpg", "title": "Erkek Yaz\u0131 Bask\u0131l\u0131 B\u00fcy\u00fck Okul S\u0131rt \u00c7antas\u0131", "price": "149,99\nTL"}, {"imgUrl": "https://dfcdn.defacto.com.tr/376/A7819AX_NS_BK27_04_01.jpg", "title": "Erkek Suni Deri Okul S\u0131rt \u00c7antas\u0131", "price": "249,99\nTL"}, {"imgUrl": "https://dfcdn.defacto.com.tr/304/Y1374AZ_NS_GR2_04_01.jpg", "title": "Erkek Kendi Kendini Onaran Su Tutmayan Kuma\u015f S\u0131rt \u00c7antas\u0131", "price": "349,99\nTL"}, {"imgUrl": "https://dfcdn.defacto.com.tr/304/A2572AX_NS_BK27_04_01.jpg", "title": "Erkek Defacto Fit NBA Chicago Bulls Su \u0130tici Kuma\u015f \u00c7apraz \u00c7anta", "price": "349,99\nTL"}, {"imgUrl": "https://dfcdn.defacto.com.tr/304/U3652AZ_NS_BK27_04_03.jpg", "title": "Erkek Silikon Etiketli Suni Deri Bel \u00c7antas\u0131", "price": "299,99\nTL"}, {"imgUrl": "https://dfcdn.defacto.com.tr/304/W4784AZ_NS_BK27_04_01.jpg", "title": "Erkek Suni Deri Okul S\u0131rt \u00c7antas\u0131", "price": "299,99\nTL"}, {"imgUrl": "https://dfcdn.defacto.com.tr/304/A2810AX_NS_NV2_04_01.jpg", "title": "Erkek Defacto Fit NBA \u00c7apraz \u00c7anta", "price": "349,99\nTL"}, {"imgUrl": "https://dfcdn.defacto.com.tr/304/Y1376AZ_NS_GR2_04_02.jpg", "title": "Erkek S\u0131rt \u00c7antas\u0131", "price": "199,99\nTL"}, {"imgUrl": "https://dfcdn.defacto.com.tr/304/U3655AZ_NS_BR2_04_02.jpg", "title": "Erkek Laptop B\u00f6lmeli Okul S\u0131rt \u00c7antas\u0131", "price": "299,99\nTL"}, {"imgUrl": "https://dfcdn.defacto.com.tr/304/Y1374AZ_NS_BR2_04_02.jpg", "title": "Erkek Kendi Kendini Onaran Su Tutmayan Kuma\u015f S\u0131rt \u00c7antas\u0131", "price": "349,99\nTL"}, {"imgUrl": "https://dfcdn.defacto.com.tr/376/W9960AZ_NS_BK27_04_02.jpg", "title": "Erkek \u00c7apraz \u00c7anta", "price": "249,99\nTL"}, {"imgUrl": "https://dfcdn.defacto.com.tr/376/X2826AZ_NS_BK27_04_02.jpg", "title": "Erkek B\u00fcy\u00fck S\u0131rt \u00c7antas\u0131", "price": "299,99\nTL"}, {"imgUrl": "https://dfcdn.defacto.com.tr/376/Z0524AZ_NS_BG26_04_02.jpg", "title": "Erkek Discovery B\u00fcy\u00fck S\u0131rt \u00c7antas\u0131", "price": "399,99\nTL"}, {"imgUrl": "https://dfcdn.defacto.com.tr/376/Y1362AZ_NS_BK27_04_02.jpg", "title": "Erkek Kendi Kendini Onaran Su Tutmayan Kuma\u015f S\u0131rt \u00c7antas\u0131", "price": "199,99\nTL"}, {"imgUrl": "https://dfcdn.defacto.com.tr/304/Y1376AZ_NS_OG37_04_01.jpg", "title": "Erkek S\u0131rt \u00c7antas\u0131", "price": "199,99\nTL"}, {"imgUrl": "https://dfcdn.defacto.com.tr/304/Z8045AZ_NS_KR1_04_01.jpg", "title": "Erkek F\u0131rat Bel \u00c7antas\u0131", "price": "199,99\nTL"}, {"imgUrl": "https://dfcdn.defacto.com.tr/304/A1034AX_NS_NV2_04_02.jpg", "title": "Erkek Su \u0130tici Kuma\u015f S\u0131rt \u00c7antas\u0131", "price": "399,99\nTL"}, {"imgUrl": "https://dfcdn.defacto.com.tr/304/A1004AX_NS_YL2_04_01.jpg", "title": "Erkek Tablet \u00c7antas\u0131", "price": "249,99\nTL"}, {"imgUrl": "https://dfcdn.defacto.com.tr/304/Y1362AZ_NS_BG26_04_02.jpg", "title": "Erkek Kendi Kendini Onaran Su Tutmayan Kuma\u015f S\u0131rt \u00c7antas\u0131", "price": "199,99\nTL"}, {"imgUrl": "https://dfcdn.defacto.com.tr/304/S5667AZ_NS_GR4_04_04.jpg", "title": "Erkek \u00c7apraz Omuz \u00c7antas\u0131", "price": "149,99\nTL"}, {"imgUrl": "https://dfcdn.defacto.com.tr/304/A0967AX_NS_BK27_04_01.jpg", "title": "Erkek Suni Deri El \u00c7antas\u0131", "price": "149,99\nTL"}, {"imgUrl": "https://dfcdn.defacto.com.tr/304/Z0523AZ_NS_BK27_04_02.jpg", "title": "Erkek Discovery B\u00fcy\u00fck S\u0131rt \u00c7antas\u0131", "price": "399,99\nTL"}, {"imgUrl": "https://dfcdn.defacto.com.tr/376/U3669AZ_NS_BK27_04_06.jpg", "title": "Erkek Spor \u00c7antas\u0131", "price": "399,99\nTL"}, {"imgUrl": "https://dfcdn.defacto.com.tr/376/W9983AZ_NS_BK27_04_02.jpg", "title": "Erkek B\u00fcy\u00fck Suni Deri Bel \u00c7antas\u0131", "price": "199,99\nTL"}, {"imgUrl": "https://dfcdn.defacto.com.tr/376/A1006AX_NS_BK27_04_01.jpg", "title": "Erkek Suni Deri \u00c7apraz \u00c7anta", "price": "249,99\nTL"}, {"imgUrl": "https://dfcdn.defacto.com.tr/376/Z1025AZ_NS_BK27_04_01.jpg", "title": "Erkek Suni Deri \u00c7apraz \u00c7anta", "price": "129,99\nTL"}, {"imgUrl": "https://dfcdn.defacto.com.tr/304/U3645AZ_NS_GR4_04_02.jpg", "title": "Erkek \u00c7apraz \u00c7anta", "price": "149,99\nTL"}, {"imgUrl": "https://dfcdn.defacto.com.tr/304/W1789AZ_NS_BK27_04_03.jpg", "title": "Erkek B\u00fcy\u00fck Suni Deri El \u00c7antas\u0131", "price": "199,99\nTL"}, {"imgUrl": "https://dfcdn.defacto.com.tr/304/U3649AZ_NS_BK27_04_03.jpg", "title": "Erkek B\u00fcy\u00fck Bel \u00c7antas\u0131", "price": "149,99\nTL"}, {"imgUrl": "https://dfcdn.defacto.com.tr/304/A1011AX_NS_BK27_04_01.jpg", "title": "Erkek Okul S\u0131rt \u00c7antas\u0131", "price": "349,99\nTL"}, {"imgUrl": "https://dfcdn.defacto.com.tr/304/Z1028AZ_NS_BK27_04_02.jpg", "title": "Erkek \u00c7apraz \u00c7anta", "price": "149,99\nTL"}, {"imgUrl": "https://dfcdn.defacto.com.tr/304/Z4110AZ_NS_BK27_04_02.jpg", "title": "Erkek Defacto Fit Ayakkab\u0131 G\u00f6zl\u00fc Spor ve Seyahat \u00c7antas\u0131", "price": "399,99\nTL"}, {"imgUrl": "https://dfcdn.defacto.com.tr/304/Y1370AZ_NS_BK27_04_02.jpg", "title": "Erkek Su \u0130tici Kuma\u015f S\u0131rt \u00c7antas\u0131", "price": "199,99\nTL"}, {"imgUrl": "https://dfcdn.defacto.com.tr/304/U3650AZ_NS_BK27_04_05.jpg", "title": "Erkek Ekstra G\u00f6zl\u00fc Ultra Hafif Bel \u00c7antas\u0131", "price": "149,99\nTL"}, {"imgUrl": "https://dfcdn.defacto.com.tr/376/U3650AZ_NS_NV2_04_01.jpg", "title": "Erkek Ekstra G\u00f6zl\u00fc Ultra Hafif Bel \u00c7antas\u0131", "price": "149,99\nTL"}, {"imgUrl": "https://dfcdn.defacto.com.tr/376/Y7062AZ_NS_BK27_04_01.jpg", "title": "Erkek \u00c7apraz \u00c7anta", "price": "99,99\nTL"}, {"imgUrl": "https://dfcdn.defacto.com.tr/376/A2010AX_NS_BK27_04_02.jpg", "title": "Erkek Zeytin Derisi Vegan \u00c7apraz \u00c7anta", "price": "699,99\nTL"}, {"imgUrl": "https://dfcdn.defacto.com.tr/376/Z4109AZ_NS_AR31_04_01.jpg", "title": "Erkek Defacto Fit \u2018Terlik & Havlu \u0130\u00e7 Cepli Spor ve Seyahat \u00c7antas\u0131", "price": "399,99\nTL"}]