[{"infoUrl": "https://static.pullandbear.net/2/photos//2023/V/0/2/p/4596/589/803/02/4596589803_4_1_8.jpg?t=1679478150316&imwidth=563", "price": "599,95 TL", "title": "\"New York County\" yaz\u0131l\u0131 sweatshirt"}, {"infoUrl": "https://static.pullandbear.net/2/photos//2023/V/0/2/p/4596/560/712/4596560712_2_6_8.jpg?t=1677170285733&imwidth=563", "price": "599,95 TL", "title": "Floklu New York bask\u0131l\u0131 sweatshirt"}, {"infoUrl": "https://static.pullandbear.net/2/photos//2023/V/0/2/p/4596/589/803/4596589803_2_6_8.jpg?t=1677576767283&imwidth=563", "price": "599,95 TL", "title": "\"New York County\" yaz\u0131l\u0131 sweatshirt"}, {"infoUrl": "https://static.pullandbear.net/2/photos//2023/V/0/2/p/4596/566/800/4596566800_2_6_8.jpg?t=1678104673074&imwidth=563", "price": "659,95 TL", "title": "\u0130\u015flemeli Paris kap\u00fc\u015fonlu sweatshirt"}, {"infoUrl": "https://static.pullandbear.net/2/photos//2023/V/0/2/p/4596/559/812/4596559812_2_6_8.jpg?t=1678104671008&imwidth=563", "price": "659,95 TL", "title": "Floklu Brooklyn bask\u0131l\u0131 kap\u00fc\u015fonlu sweatshirt"}, {"infoUrl": "https://static.pullandbear.net/2/photos//2023/V/0/2/p/8593/530/812/8593530812_2_6_8.jpg?t=1677179613529&imwidth=563", "price": "699,95 TL", "title": "NFL New York Jets kap\u00fc\u015fonlu sweatshirt"}, {"infoUrl": "https://static.pullandbear.net/2/photos//2023/V/0/2/p/8591/513/819/02/8591513819_4_1_8.jpg?t=1669892725310&imwidth=563", "price": "429,95 TL", "title": "Kap\u00fc\u015fonlu basic sweatshirt"}, {"infoUrl": "https://static.pullandbear.net/2/photos//2023/V/0/2/p/8591/513/800/8591513800_2_6_8.jpg?t=1678969274181&imwidth=563", "price": "429,95 TL", "title": "Kap\u00fc\u015fonlu basic sweatshirt"}, {"infoUrl": "https://static.pullandbear.net/2/photos//2023/V/0/2/p/8591/513/250/8591513250_2_6_8.jpg?t=1678968995900&imwidth=563", "price": "429,95 TL", "title": "Kap\u00fc\u015fonlu basic sweatshirt"}, {"infoUrl": "https://static.pullandbear.net/2/photos//2023/V/0/2/p/8591/513/807/8591513807_2_6_8.jpg?t=1678968995764&imwidth=563", "price": "429,95 TL", "title": "Kap\u00fc\u015fonlu basic sweatshirt"}, {"infoUrl": "https://static.pullandbear.net/2/photos//2023/V/0/2/p/8591/513/501/8591513501_2_6_8.jpg?t=1677171194354&imwidth=563", "price": "429,95 TL", "title": "Kap\u00fc\u015fonlu basic sweatshirt"}, {"infoUrl": "https://static.pullandbear.net/2/photos//2023/V/0/2/p/8591/513/717/8591513717_2_6_8.jpg?t=1677171194473&imwidth=563", "price": "429,95 TL", "title": "Kap\u00fc\u015fonlu basic sweatshirt"}, {"infoUrl": "https://static.pullandbear.net/2/photos//2023/V/0/2/p/4596/923/800/02/4596923800_4_1_8.jpg?t=1674035768718&imwidth=563", "price": "599,95 TL", "title": "Fermuarl\u0131 kap\u00fc\u015fonlu sweatshirt"}, {"infoUrl": "https://static.pullandbear.net/2/photos//2023/V/0/2/p/4596/923/803/4596923803_2_6_8.jpg?t=1677170336854&imwidth=563", "price": "599,95 TL", "title": "Fermuarl\u0131 kap\u00fc\u015fonlu sweatshirt"}, {"infoUrl": "https://static.pullandbear.net/2/photos//2023/V/0/2/p/4596/923/800/4596923800_2_6_8.jpg?t=1677170336782&imwidth=563", "price": "599,95 TL", "title": "Fermuarl\u0131 kap\u00fc\u015fonlu sweatshirt"}, {"infoUrl": "https://static.pullandbear.net/2/photos//2023/V/0/2/p/4596/923/712/4596923712_2_6_8.jpg?t=1677170336713&imwidth=563", "price": "599,95 TL", "title": "Fermuarl\u0131 kap\u00fc\u015fonlu sweatshirt"}, {"infoUrl": "https://static.pullandbear.net/2/photos//2023/V/0/2/p/4596/576/803/02/4596576803_4_1_8.jpg?t=1675697593133&imwidth=563", "price": "461,95 TL\n599,95 TL\n659,95 TL", "title": "Logo yamal\u0131 kolej kap\u00fc\u015fonlu sweatshirt"}, {"infoUrl": "https://static.pullandbear.net/2/photos//2023/V/0/2/p/4596/576/803/4596576803_2_6_8.jpg?t=1678104704441&imwidth=563", "price": "461,95 TL\n599,95 TL\n659,95 TL", "title": "Logo yamal\u0131 kolej kap\u00fc\u015fonlu sweatshirt"}, {"infoUrl": "https://static.pullandbear.net/2/photos//2023/V/0/2/p/4596/595/800/03/4596595800_4_1_8.jpg?t=1675170908071&imwidth=563", "price": "659,95 TL", "title": "STWD bask\u0131l\u0131 kap\u00fc\u015fonlu sweatshirt"}, {"infoUrl": "https://static.pullandbear.net/2/photos//2023/V/0/2/p/4596/595/711/4596595711_2_6_8.jpg?t=1678104782211&imwidth=563", "price": "659,95 TL", "title": "STWD bask\u0131l\u0131 kap\u00fc\u015fonlu sweatshirt"}, {"infoUrl": "https://static.pullandbear.net/2/photos//2023/V/0/2/p/4596/595/800/4596595800_2_6_8.jpg?t=1677170379083&imwidth=563", "price": "659,95 TL", "title": "STWD bask\u0131l\u0131 kap\u00fc\u015fonlu sweatshirt"}, {"infoUrl": "https://static.pullandbear.net/2/photos//2023/V/0/2/p/8597/524/802/03/8597524802_4_1_8.jpg?t=1676632473834&imwidth=563", "price": "829,95 TL", "title": "Gri Naruto bask\u0131l\u0131 kap\u00fc\u015fonlu sweatshirt"}, {"infoUrl": "https://static.pullandbear.net/2/photos//2023/V/0/2/p/8593/523/800/8593523800_2_6_8.jpg?t=1677179609535&imwidth=563", "price": "699,95 TL", "title": "One Piece bask\u0131l\u0131 kap\u00fc\u015fonlu sweatshirt"}, {"infoUrl": "https://static.pullandbear.net/2/photos//2023/V/0/2/p/4596/535/802/4596535802_2_6_8.jpg?t=1677170265752&imwidth=563", "price": "461,95 TL\n659,95 TL", "title": "One Piece bask\u0131l\u0131 kap\u00fc\u015fonlu sweatshirt"}, {"infoUrl": "https://static.pullandbear.net/2/photos//2023/V/0/2/p/4596/548/250/03/4596548250_4_1_8.jpg?t=1676892279344&imwidth=563", "price": "599,95 TL", "title": "STWD grafik bask\u0131l\u0131 kap\u00fc\u015fonlu sweatshirt"}, {"infoUrl": "https://static.pullandbear.net/2/photos//2023/V/0/2/p/4596/548/800/4596548800_2_6_8.jpg?t=1677170256950&imwidth=563", "price": "419,95 TL\n559,95 TL\n599,95 TL", "title": "STWD grafik bask\u0131l\u0131 kap\u00fc\u015fonlu sweatshirt"}, {"infoUrl": "https://static.pullandbear.net/2/photos//2023/V/0/2/p/4596/548/250/4596548250_2_6_8.jpg?t=1677170256618&imwidth=563", "price": "599,95 TL", "title": "STWD grafik bask\u0131l\u0131 kap\u00fc\u015fonlu sweatshirt"}, {"infoUrl": "https://static.pullandbear.net/2/photos//2023/V/0/2/p/4596/548/501/4596548501_2_6_8.jpg?t=1677170256718&imwidth=563", "price": "419,95 TL\n559,95 TL\n599,95 TL", "title": "STWD grafik bask\u0131l\u0131 kap\u00fc\u015fonlu sweatshirt"}, {"infoUrl": "https://static.pullandbear.net/2/photos//2023/V/0/2/p/4596/564/500/4596564500_2_6_8.jpg?t=1677170267293&imwidth=563", "price": "359,95 TL\n391,95 TL\n599,95 TL", "title": "Ombre desenli sweatshirt"}, {"infoUrl": "https://static.pullandbear.net/2/photos//2023/V/0/2/p/4596/574/800/4596574800_2_6_8.jpg?t=1677170359568&imwidth=563", "price": "359,95 TL\n559,95 TL", "title": "\u00c7i\u00e7ek desenli yamal\u0131 sweatshirt"}, {"infoUrl": "https://static.pullandbear.net/2/photos//2023/V/0/2/p/8593/506/802/02/8593506802_4_1_8.jpg?t=1662985694123&imwidth=563", "price": "489,95 TL\n659,95 TL\n699,95 TL", "title": "Gri kap\u00fc\u015fonlu Rocky Balboa bask\u0131l\u0131 sweatshirt"}, {"infoUrl": "https://static.pullandbear.net/2/photos//2023/V/0/2/p/8593/900/800/8593900800_2_6_8.jpg?t=1677179614310&imwidth=563", "price": "699,95 TL", "title": "Rocky Balboa kap\u00fc\u015fonlu sweatshirt"}, {"infoUrl": "https://static.pullandbear.net/2/photos//2023/V/0/2/p/8593/506/802/8593506802_2_6_8.jpg?t=1677179600322&imwidth=563", "price": "489,95 TL\n659,95 TL\n699,95 TL", "title": "Gri kap\u00fc\u015fonlu Rocky Balboa bask\u0131l\u0131 sweatshirt"}, {"infoUrl": "https://static.pullandbear.net/2/photos//2023/V/0/2/p/4596/551/505/4596551505_2_6_8.jpg?t=1677170248030&imwidth=563", "price": "461,95 TL\n599,95 TL\n659,95 TL", "title": "Haki kap\u00fc\u015fonlu sweatshirt"}, {"infoUrl": "https://static.pullandbear.net/2/photos//2023/V/0/2/p/4590/511/251/4590511251_2_6_8.jpg?t=1677169725124&imwidth=563", "price": "391,95 TL\n559,95 TL", "title": "Yaz\u0131 i\u015flemeli, kap\u00fc\u015fonlu sweatshirt"}, {"infoUrl": "https://static.pullandbear.net/2/photos//2023/V/0/2/p/4596/579/712/4596579712_4_1_8.jpg?t=1676904875924&imwidth=563", "price": "399,95 TL", "title": "Basic pamuklu t-shirt"}, {"infoUrl": "https://static.pullandbear.net/2/photos//2023/V/0/2/p/4596/579/251/4596579251_2_6_8.jpg?t=1677170362032&imwidth=563", "price": "399,95 TL", "title": "Basic pamuklu t-shirt"}, {"infoUrl": "https://static.pullandbear.net/2/photos//2023/V/0/2/p/4596/579/800/4596579800_2_6_8.jpg?t=1677170362199&imwidth=563", "price": "399,95 TL", "title": "Basic pamuklu t-shirt"}, {"infoUrl": "https://static.pullandbear.net/2/photos//2023/V/0/2/p/8593/916/982/8593916982_2_6_8.jpg?t=1677171282542&imwidth=563", "price": "359,95 TL\n659,95 TL", "title": "Dragon Ball sweatshirt"}, {"infoUrl": "https://static.pullandbear.net/2/photos//2023/V/0/2/p/8591/513/300/02/8591513300_4_1_8.jpg?t=1672749309350&imwidth=563", "price": "429,95 TL", "title": "Kap\u00fc\u015fonlu basic sweatshirt"}, {"infoUrl": "https://static.pullandbear.net/2/photos//2023/V/0/2/p/8591/513/620/8591513620_2_6_8.jpg?t=1677171193971&imwidth=563", "price": "429,95 TL", "title": "Kap\u00fc\u015fonlu basic sweatshirt"}, {"infoUrl": "https://static.pullandbear.net/2/photos//2023/V/0/2/p/8591/513/404/8591513404_2_6_8.jpg?t=1677177227905&imwidth=563", "price": "429,95 TL", "title": "Kap\u00fc\u015fonlu basic sweatshirt"}, {"infoUrl": "https://static.pullandbear.net/2/photos//2023/V/0/2/p/8591/513/526/8591513526_2_6_8.jpg?t=1677179596322&imwidth=563", "price": "429,95 TL", "title": "Kap\u00fc\u015fonlu basic sweatshirt"}, {"infoUrl": "https://static.pullandbear.net/2/photos//2023/V/0/2/p/8591/513/819/8591513819_2_6_8.jpg?t=1677171193614&imwidth=563", "price": "429,95 TL", "title": "Kap\u00fc\u015fonlu basic sweatshirt"}, {"infoUrl": "https://static.pullandbear.net/2/photos//2023/V/0/2/p/8591/513/803/8591513803_2_6_8.jpg?t=1678968995502&imwidth=563", "price": "429,95 TL", "title": "Kap\u00fc\u015fonlu basic sweatshirt"}, {"infoUrl": "https://static.pullandbear.net/2/photos//2023/V/0/2/p/4596/704/711/4596704711_2_6_8.jpg?t=1677170354806&imwidth=563", "price": "529,95 TL", "title": "K\u0131sa kollu kabartmal\u0131 t-shirt"}, {"infoUrl": "https://static.pullandbear.net/2/photos//2023/V/0/2/p/4596/580/802/02/4596580802_4_1_8.jpg?t=1676373906461&imwidth=563", "price": "321,95 TL\n429,95 TL\n459,95 TL", "title": "\u00c7izgili sweatshirt"}, {"infoUrl": "https://static.pullandbear.net/2/photos//2023/V/0/2/p/4596/580/710/4596580710_2_6_8.jpg?t=1677170366033&imwidth=563", "price": "459,95 TL", "title": "\u00c7izgili sweatshirt"}, {"infoUrl": "https://static.pullandbear.net/2/photos//2023/V/0/2/p/4596/580/711/4596580711_2_6_8.jpg?t=1677170365972&imwidth=563", "price": "459,95 TL", "title": "\u00c7izgili sweatshirt"}, {"infoUrl": "https://static.pullandbear.net/2/photos//2023/V/0/2/p/4596/580/403/4596580403_2_6_8.jpg?t=1677170365879&imwidth=563", "price": "459,95 TL", "title": "\u00c7izgili sweatshirt"}, {"infoUrl": "https://static.pullandbear.net/2/photos//2023/V/0/2/p/4596/580/802/4596580802_2_6_8.jpg?t=1677170366087&imwidth=563", "price": "321,95 TL\n429,95 TL\n459,95 TL", "title": "\u00c7izgili sweatshirt"}, {"infoUrl": "https://static.pullandbear.net/2/photos//2023/V/0/2/p/3593/514/251/02/3593514251_4_1_8.jpg?t=1678703654437&imwidth=563", "price": "659,95 TL", "title": "STWD bask\u0131l\u0131 kap\u00fc\u015fonlu sweatshirt"}, {"infoUrl": "https://static.pullandbear.net/2/photos//2023/V/0/2/p/3593/514/251/3593514251_2_6_8.jpg?t=1678270087418&imwidth=563", "price": "659,95 TL", "title": "STWD bask\u0131l\u0131 kap\u00fc\u015fonlu sweatshirt"}, {"infoUrl": "https://static.pullandbear.net/2/photos//2023/V/0/2/p/3593/515/717/3593515717_2_6_8.jpg?t=1678270083712&imwidth=563", "price": "599,95 TL", "title": "New Champs sweatshirt"}, {"infoUrl": "https://static.pullandbear.net/2/photos//2023/V/0/2/p/4596/585/811/03/4596585811_4_1_8.jpg?t=1675942708711&imwidth=563", "price": "659,95 TL", "title": "Geometrik desenli triko kap\u00fc\u015fonlu sweatshirt"}, {"infoUrl": "https://static.pullandbear.net/2/photos//2023/V/0/2/p/4596/584/800/4596584800_2_6_8.jpg?t=1677178489554&imwidth=563", "price": "659,95 TL", "title": "Floklu kelebek bask\u0131l\u0131 sweatshirt"}, {"infoUrl": "https://static.pullandbear.net/2/photos//2023/V/0/2/p/4596/585/811/4596585811_2_6_8.jpg?t=1677170377645&imwidth=563", "price": "659,95 TL", "title": "Geometrik desenli triko kap\u00fc\u015fonlu sweatshirt"}, {"infoUrl": "https://static.pullandbear.net/2/photos//2023/V/0/2/p/4596/583/779/4596583779_2_6_8.jpg?t=1677170376817&imwidth=563", "price": "599,95 TL", "title": "B\u00f6cek i\u015flemeli sweatshirt"}, {"infoUrl": "https://static.pullandbear.net/2/photos//2023/V/0/2/p/4596/569/800/4596569800_2_6_8.jpg?t=1677170353194&imwidth=563", "price": "419,95 TL\n599,95 TL\n659,95 TL", "title": "Flok bask\u0131l\u0131 kap\u00fc\u015fonlu sweatshirt"}, {"infoUrl": "https://static.pullandbear.net/2/photos//2023/V/0/2/p/4596/558/712/4596558712_2_6_8.jpg?t=1677170257208&imwidth=563", "price": "659,95 TL", "title": "Teknik Cosmic Dancer sweatshirt'\u00fc"}, {"infoUrl": "https://static.pullandbear.net/2/photos//2023/V/0/2/p/8591/513/250/02/8591513250_4_1_8.jpg?t=1663670134122&imwidth=563", "price": "429,95 TL", "title": "Kap\u00fc\u015fonlu basic sweatshirt"}, {"infoUrl": "https://static.pullandbear.net/2/photos//2023/V/0/2/p/8591/513/712/8591513712_2_6_8.jpg?t=1678827250869&imwidth=563", "price": "429,95 TL", "title": "Kap\u00fc\u015fonlu basic sweatshirt"}, {"infoUrl": "https://static.pullandbear.net/2/photos//2023/V/0/2/p/8591/513/403/8591513403_2_6_8.jpg?t=1679591532694&imwidth=563", "price": "429,95 TL", "title": "Kap\u00fc\u015fonlu basic sweatshirt"}, {"infoUrl": "https://static.pullandbear.net/2/photos//2023/V/0/2/p/8591/513/612/8591513612_2_6_8.jpg?t=1677171193313&imwidth=563", "price": "429,95 TL", "title": "Kap\u00fc\u015fonlu basic sweatshirt"}, {"infoUrl": "https://static.pullandbear.net/2/photos//2023/V/0/2/p/8591/513/300/8591513300_2_6_8.jpg?t=1679477625788&imwidth=563", "price": "429,95 TL", "title": "Kap\u00fc\u015fonlu basic sweatshirt"}, {"infoUrl": "https://static.pullandbear.net/2/photos//2023/V/0/2/p/8593/514/501/02/8593514501_4_1_8.jpg?t=1660658206754&imwidth=563", "price": "399,95 TL", "title": "Uzun kollu bisiklet yaka basic sweatshirt"}, {"infoUrl": "https://static.pullandbear.net/2/photos//2023/V/0/2/p/8593/514/800/8593514800_2_6_8.jpg?t=1678803397699&imwidth=563", "price": "399,95 TL", "title": "Uzun kollu bisiklet yaka basic sweatshirt"}, {"infoUrl": "https://static.pullandbear.net/2/photos//2023/V/0/2/p/8593/514/712/8593514712_2_6_8.jpg?t=1678803397642&imwidth=563", "price": "399,95 TL", "title": "Uzun kollu bisiklet yaka basic sweatshirt"}, {"infoUrl": "https://static.pullandbear.net/2/photos//2023/V/0/2/p/8593/514/501/8593514501_2_6_8.jpg?t=1678969274063&imwidth=563", "price": "399,95 TL", "title": "Uzun kollu bisiklet yaka basic sweatshirt"}, {"infoUrl": "https://static.pullandbear.net/2/photos//2023/V/0/2/p/8593/514/518/8593514518_2_6_8.jpg?t=1679592127011&imwidth=563", "price": "399,95 TL", "title": "Uzun kollu bisiklet yaka basic sweatshirt"}]