[
  {
    "infoUrl": "https://static.e-stradivarius.net/5/photos3/2023/V/0/1/p/1914/527/004/03/1914527004_10_10_1.jpg?t=1677514948726&impolicy=stradivarius-itxmediumhigh&imwidth=572&imformat=chrome&imdensity=1",
    "price": "699,95 TL",
    "title": "D\u00f6k\u00fcml\u00fc crop blazer"
  },
  {
    "infoUrl": "https://static.e-stradivarius.net/5/photos3/2023/V/0/1/p/1914/527/133/01/1914527133_1_1_1.jpg?t=1678358223608&impolicy=stradivarius-itxmediumhigh&imwidth=572&imformat=chrome&imdensity=1",
    "price": "529,95 TL",
    "title": "D\u00f6k\u00fcml\u00fc crop blazer"
  },
  {
    "infoUrl": "https://static.e-stradivarius.net/5/photos3/2023/V/0/1/p/4562/527/004/4562527004_10_1_1.jpg?t=1677600668462&impolicy=stradivarius-itxmediumhigh&imwidth=572&imformat=chrome&imdensity=1",
    "price": "529,95 TL",
    "title": "Straight fit uzun pantolon"
  },
  {
    "infoUrl": "https://static.e-stradivarius.net/5/photos3/2023/V/0/1/p/4562/925/001/4562925001_2_4_1.jpg?t=1669722876180&impolicy=stradivarius-itxmediumhigh&imwidth=572&imformat=chrome&imdensity=1",
    "price": "529,95 TL",
    "title": "Klasik straight fit pantolon"
  },
  {
    "infoUrl": "https://static.e-stradivarius.net/5/photos3/2023/V/0/1/p/1900/526/550/02/1900526550_10_10_1.jpg?t=1677514945410&impolicy=stradivarius-itxmediumhigh&imwidth=572&imformat=chrome&imdensity=1",
    "price": "829,95 TL",
    "title": "D\u00f6k\u00fcml\u00fc straight fit blazer"
  },
  {
    "infoUrl": "https://static.e-stradivarius.net/5/photos3/2023/V/0/1/p/1900/526/550/03/1900526550_10_1_1.jpg?t=1679502422976&impolicy=stradivarius-itxmediumhigh&imwidth=572&imformat=chrome&imdensity=1",
    "price": "829,95 TL",
    "title": "D\u00f6k\u00fcml\u00fc straight fit blazer"
  },
  {
    "infoUrl": "https://static.e-stradivarius.net/5/photos3/2023/V/0/1/p/1900/526/450/02/1900526450_8_1_4.jpg?t=1677581462745&impolicy=stradivarius-itxmediumhigh&imwidth=1162&imformat=chrome&imdensity=1",
    "price": "599,95 TL",
    "title": "D\u00f6k\u00fcml\u00fc straight fit blazer"
  },
  {
    "infoUrl": "https://static.e-stradivarius.net/5/photos3/2023/V/0/1/p/1900/526/048/01/1900526048_8_1_4.jpg?t=1677515659994&impolicy=stradivarius-itxmediumhigh&imwidth=1162&imformat=chrome&imdensity=1",
    "price": "599,95 TL",
    "title": "D\u00f6k\u00fcml\u00fc straight fit blazer"
  },
  {
    "infoUrl": "https://static.e-stradivarius.net/5/photos3/2023/V/0/1/p/1918/531/004/03/1918531004_10_10_1.jpg?t=1677578352673&impolicy=stradivarius-itxmediumhigh&imwidth=572&imformat=chrome&imdensity=1",
    "price": "599,95 TL",
    "title": "D\u00fc\u011fmeli blazer"
  },
  {
    "infoUrl": "https://static.e-stradivarius.net/5/photos3/2023/V/0/1/p/1183/438/430/05/1183438430_10_1_1.jpg?t=1676907943130&impolicy=stradivarius-itxmediumhigh&imwidth=572&imformat=chrome&imdensity=1",
    "price": "699,95 TL",
    "title": "K\u0131vr\u0131k belli pantolon"
  },
  {
    "infoUrl": "https://static.e-stradivarius.net/5/photos3/2023/V/0/1/p/1183/438/001/1183438001_2_4_1.jpg?t=1678780609238&impolicy=stradivarius-itxmediumhigh&imwidth=572&imformat=chrome&imdensity=1",
    "price": "699,95 TL",
    "title": "K\u0131vr\u0131k belli pantolon"
  },
  {
    "infoUrl": "https://static.e-stradivarius.net/5/photos3/2023/V/0/1/p/1184/488/001/07/1184488001_10_10_1.jpg?t=1679301365209&impolicy=stradivarius-itxmediumhigh&imwidth=572&imformat=chrome&imdensity=1",
    "price": "599,95 TL",
    "title": "Pensli smart pantolon"
  },
  {
    "infoUrl": "https://static.e-stradivarius.net/5/photos3/2023/V/0/1/p/1184/488/433/1184488433_2_4_1.jpg?t=1678780959579&impolicy=stradivarius-itxmediumhigh&imwidth=572&imformat=chrome&imdensity=1",
    "price": "599,95 TL",
    "title": "Pensli smart pantolon"
  },
  {
    "infoUrl": "https://static.e-stradivarius.net/5/photos3/2023/V/0/1/p/5953/217/430/5953217430_10_3_1.jpg?t=1676971556124&impolicy=stradivarius-itxmediumhigh&imwidth=572&imformat=chrome&imdensity=1",
    "price": "599,95 TL",
    "title": "Basic k\u0131sa yelek"
  },
  {
    "infoUrl": "https://static.e-stradivarius.net/5/photos3/2023/V/0/1/p/5953/217/001/5953217001_1_1_1.jpg?t=1678358230696&impolicy=stradivarius-itxmediumhigh&imwidth=572&imformat=chrome&imdensity=1",
    "price": "699,95 TL",
    "title": "Basic k\u0131sa yelek"
  },
  {
    "infoUrl": "https://static.e-stradivarius.net/5/photos3/2023/V/0/1/p/1918/531/001/06/1918531001_10_10_1.jpg?t=1677578352532&impolicy=stradivarius-itxmediumhigh&imwidth=572&imformat=chrome&imdensity=1",
    "price": "599,95 TL",
    "title": "D\u00fc\u011fmeli blazer"
  },
  {
    "infoUrl": "https://static.e-stradivarius.net/5/photos3/2023/V/0/1/p/1916/918/450/03/1916918450_8_1_4.jpg?t=1677516010355&impolicy=stradivarius-itxmediumhigh&imwidth=1162&imformat=chrome&imdensity=1",
    "price": "459,95 TL",
    "title": "\u00c7izgili straight fit blazer"
  },
  {
    "infoUrl": "https://static.e-stradivarius.net/5/photos3/2023/V/0/1/p/1918/531/552/02/1918531552_10_10_1.jpg?t=1677514931087&impolicy=stradivarius-itxmediumhigh&imwidth=572&imformat=chrome&imdensity=1",
    "price": "829,95 TL",
    "title": "D\u00fc\u011fmeli blazer"
  },
  {
    "infoUrl": "https://static.e-stradivarius.net/5/photos3/2023/V/0/1/p/1918/531/001/1918531001_2_4_1.jpg?t=1678780944459&impolicy=stradivarius-itxmediumhigh&imwidth=572&imformat=chrome&imdensity=1",
    "price": "599,95 TL",
    "title": "D\u00fc\u011fmeli blazer"
  },
  {
    "infoUrl": "https://static.e-stradivarius.net/5/photos3/2023/V/0/1/p/1916/916/140/01/1916916140_8_1_4.jpg?t=1677162426611&impolicy=stradivarius-itxmediumhigh&imwidth=1162&imformat=chrome&imdensity=1",
    "price": "459,95 TL",
    "title": "Bal\u0131ks\u0131rt\u0131 straight fit blazer"
  },
  {
    "infoUrl": "https://static.e-stradivarius.net/5/photos3/2023/V/0/1/p/1916/916/004/1916916004_2_1_1.jpg?t=1677495921141&impolicy=stradivarius-itxmediumhigh&imwidth=572&imformat=chrome&imdensity=1",
    "price": "599,95 TL",
    "title": "Bal\u0131ks\u0131rt\u0131 straight fit blazer"
  },
  {
    "infoUrl": "https://static.e-stradivarius.net/5/photos3/2023/V/0/1/p/1926/569/430/1926569430_1_1_1.jpg?t=1678723273957&impolicy=stradivarius-itxmediumhigh&imwidth=572&imformat=chrome&imdensity=1",
    "price": "459,95 TL",
    "title": "Rustik crop blazer"
  },
  {
    "infoUrl": "https://static.e-stradivarius.net/5/photos3/2023/V/0/1/p/1926/569/456/1926569456_1_1_1.jpg?t=1680074332306&impolicy=stradivarius-itxmediumhigh&imwidth=572&imformat=chrome&imdensity=1",
    "price": "699,95 TL",
    "title": "Rustik crop blazer"
  },
  {
    "infoUrl": "https://static.e-stradivarius.net/5/photos3/2023/V/0/1/p/1918/531/001/04/1918531001_8_1_4.jpg?t=1677516030228&impolicy=stradivarius-itxmediumhigh&imwidth=1162&imformat=chrome&imdensity=1",
    "price": "459,95 TL",
    "title": "D\u00fc\u011fmeli blazer"
  },
  {
    "infoUrl": "https://static.e-stradivarius.net/5/photos3/2023/V/0/1/p/1914/527/001/01/1914527001_8_1_4.jpg?t=1677515661308&impolicy=stradivarius-itxmediumhigh&imwidth=1162&imformat=chrome&imdensity=1",
    "price": "699,95 TL",
    "title": "D\u00f6k\u00fcml\u00fc crop blazer"
  },
  {
    "infoUrl": "https://static.e-stradivarius.net/5/photos3/2023/V/0/1/p/1914/460/456/1914460456_2_4_1.jpg?t=1678720940799&impolicy=stradivarius-itxmediumhigh&imwidth=572&imformat=chrome&imdensity=1",
    "price": "699,95 TL",
    "title": "D\u00f6k\u00fcml\u00fc crop blazer"
  },
  {
    "infoUrl": "https://static.e-stradivarius.net/5/photos3/2023/V/0/1/p/1928/570/430/1928570430_2_1_1.jpg?t=1679059107614&impolicy=stradivarius-itxmediumhigh&imwidth=572&imformat=chrome&imdensity=1",
    "price": "599,95 TL",
    "title": "D\u00fcz rustik blazer"
  },
  {
    "infoUrl": "https://static.e-stradivarius.net/5/photos3/2023/V/0/1/p/1900/459/004/02/1900459004_1_1_1.jpg?t=1679502127391&impolicy=stradivarius-itxmediumhigh&imwidth=572&imformat=chrome&imdensity=1",
    "price": "599,95 TL",
    "title": "D\u00f6k\u00fcml\u00fc straight fit blazer"
  },
  {
    "infoUrl": "https://static.e-stradivarius.net/5/photos3/2023/V/0/1/p/1900/459/004/1900459004_1_1_1.jpg?t=1678266386772&impolicy=stradivarius-itxmediumhigh&imwidth=572&imformat=chrome&imdensity=1",
    "price": "599,95 TL",
    "title": "D\u00f6k\u00fcml\u00fc straight fit blazer"
  },
  {
    "infoUrl": "https://static.e-stradivarius.net/5/photos3/2023/V/0/1/p/1936/799/045/1936799045_10_2_1.jpg?t=1678287636739&impolicy=stradivarius-itxmediumhigh&imwidth=572&imformat=chrome&imdensity=1",
    "price": "599,95 TL",
    "title": "Straight fit blazer"
  },
  {
    "infoUrl": "https://static.e-stradivarius.net/5/photos3/2023/V/0/1/p/1187/718/552/1187718552_2_4_1.jpg?t=1680168541595&impolicy=stradivarius-itxmediumhigh&imwidth=572&imformat=chrome&imdensity=1",
    "price": "599,95 TL",
    "title": "Spor uzun bol pa\u00e7a pantolon"
  },
  {
    "infoUrl": "https://static.e-stradivarius.net/5/photos3/2023/V/0/1/p/1185/526/048/1185526048_1_1_1.jpg?t=1677495588245&impolicy=stradivarius-itxmediumhigh&imwidth=572&imformat=chrome&imdensity=1",
    "price": "829,95 TL",
    "title": "Pilili smart pantolon"
  },
  {
    "infoUrl": "https://static.e-stradivarius.net/5/photos3/2023/V/0/1/p/1934/525/001/1934525001_1_1_1.jpg?t=1677245423336&impolicy=stradivarius-itxmediumhigh&imwidth=572&imformat=chrome&imdensity=1",
    "price": "599,95 TL",
    "title": "Oversize blazer"
  },
  {
    "infoUrl": "https://static.e-stradivarius.net/5/photos3/2023/V/0/1/p/1926/569/552/1926569552_1_1_1.jpg?t=1678723274105&impolicy=stradivarius-itxmediumhigh&imwidth=572&imformat=chrome&imdensity=1",
    "price": "529,95 TL",
    "title": "Rustik crop blazer"
  },
  {
    "infoUrl": "https://static.e-stradivarius.net/5/photos3/2023/V/0/1/p/1928/570/004/1928570004_2_1_1.jpg?t=1679395638437&impolicy=stradivarius-itxmediumhigh&imwidth=572&imformat=chrome&imdensity=1",
    "price": "599,95 TL",
    "title": "D\u00fcz rustik blazer"
  },
  {
    "infoUrl": "https://static.e-stradivarius.net/5/photos3/2023/V/0/1/p/5953/217/004/5953217004_2_2_1.jpg?t=1677230410342&impolicy=stradivarius-itxmediumhigh&imwidth=572&imformat=chrome&imdensity=1",
    "price": "599,95 TL",
    "title": "Basic k\u0131sa yelek"
  },
  {
    "infoUrl": "https://static.e-stradivarius.net/5/photos3/2023/V/0/1/p/1186/717/430/01/1186717430_2_10_1.jpg?t=1679658485115&impolicy=stradivarius-itxmediumhigh&imwidth=572&imformat=chrome&imdensity=1",
    "price": "599,95 TL",
    "title": "Rustik Smart pantolon"
  },
  {
    "infoUrl": "https://static.e-stradivarius.net/5/photos3/2023/V/0/1/p/1128/504/456/1128504456_10_1_1.jpg?t=1675763809312&impolicy=stradivarius-itxmediumhigh&imwidth=572&imformat=chrome&imdensity=1",
    "price": "459,95 TL",
    "title": "Pa\u00e7alar\u0131 y\u0131rtma\u00e7l\u0131 pantolon"
  },
  {
    "infoUrl": "https://static.e-stradivarius.net/5/photos3/2023/V/0/1/p/1128/504/001/1128504001_2_4_1.jpg?t=1678780590227&impolicy=stradivarius-itxmediumhigh&imwidth=572&imformat=chrome&imdensity=1",
    "price": "459,95 TL",
    "title": "Pa\u00e7alar\u0131 y\u0131rtma\u00e7l\u0131 pantolon"
  },
  {
    "infoUrl": "https://static.e-stradivarius.net/5/photos3/2023/V/0/1/p/1266/526/450/01/1266526450_10_10_1.jpg?t=1679654884471&impolicy=stradivarius-itxmediumhigh&imwidth=572&imformat=chrome&imdensity=1",
    "price": "459,95 TL",
    "title": "Ba\u011fc\u0131kl\u0131 d\u00f6k\u00fcml\u00fc \u015fort etek"
  },
  {
    "infoUrl": "https://static.e-stradivarius.net/5/photos3/2023/V/0/1/p/1266/526/450/1266526450_2_4_1.jpg?t=1679664620297&impolicy=stradivarius-itxmediumhigh&imwidth=572&imformat=chrome&imdensity=1",
    "price": "459,95 TL",
    "title": "Ba\u011fc\u0131kl\u0131 d\u00f6k\u00fcml\u00fc \u015fort etek"
  },
  {
    "infoUrl": "https://static.e-stradivarius.net/5/photos3/2023/V/0/1/p/1914/460/010/01/1914460010_10_10_1.jpg?t=1677514938883&impolicy=stradivarius-itxmediumhigh&imwidth=572&imformat=chrome&imdensity=1",
    "price": "529,95 TL",
    "title": "D\u00f6k\u00fcml\u00fc crop blazer"
  },
  {
    "infoUrl": "https://static.e-stradivarius.net/5/photos3/2023/V/0/1/p/1266/526/550/01/1266526550_2_10_1.jpg?t=1679654884532&impolicy=stradivarius-itxmediumhigh&imwidth=572&imformat=chrome&imdensity=1",
    "price": "459,95 TL",
    "title": "Ba\u011fc\u0131kl\u0131 d\u00f6k\u00fcml\u00fc \u015fort etek"
  },
  {
    "infoUrl": "https://static.e-stradivarius.net/5/photos3/2023/V/0/1/p/1918/531/040/01/1918531040_8_1_4.jpg?t=1677516030681&impolicy=stradivarius-itxmediumhigh&imwidth=1162&imformat=chrome&imdensity=1",
    "price": "829,95 TL",
    "title": "D\u00fc\u011fmeli blazer"
  },
  {
    "infoUrl": "https://static.e-stradivarius.net/5/photos3/2023/V/0/1/p/1916/532/048/1916532048_1_1_1.jpg?t=1677669130575&impolicy=stradivarius-itxmediumhigh&imwidth=572&imformat=chrome&imdensity=1",
    "price": "459,95 TL",
    "title": "Casual fit d\u00fc\u011fmeli blazer"
  }
]
