[{"infoUrl": "https://static.e-stradivarius.net/5/photos3/2023/V/0/1/p/1381/381/141/04/1381381141_2_10_1.jpg?t=1680507366832&impolicy=stradivarius-itxmediumhigh&imwidth=572&imformat=chrome&imdensity=1", "price": "359,95 TL", "title": "D\u00f6k\u00fcml\u00fc spor \u015fort"}, {"infoUrl": "https://static.e-stradivarius.net/5/photos3/2023/V/0/1/p/1381/381/001/1381381001_2_2_1.jpg?t=1677770846410&impolicy=stradivarius-itxmediumhigh&imwidth=572&imformat=chrome&imdensity=1", "price": "359,95 TL", "title": "D\u00f6k\u00fcml\u00fc spor \u015fort"}, {"infoUrl": "https://static.e-stradivarius.net/5/photos3/2023/V/0/1/p/7663/256/200/02/7663256200_8_1_4.jpg?t=1680507475016&impolicy=stradivarius-itxmediumhigh&imwidth=1162&imformat=chrome&imdensity=1", "price": "359,95 TL", "title": "Soluk efektli bisiklet\u00e7i tayt\u0131"}, {"infoUrl": "https://static.e-stradivarius.net/5/photos3/2023/V/0/1/p/7663/256/501/7663256501_6_1_1.jpg?t=1678781462094&impolicy=stradivarius-itxmediumhigh&imwidth=572&imformat=chrome&imdensity=1", "price": "359,95 TL", "title": "Soluk efektli bisiklet\u00e7i tayt\u0131"}, {"infoUrl": "https://static.e-stradivarius.net/5/photos3/2023/V/0/1/p/1381/381/004/04/1381381004_2_10_1.jpg?t=1680507358065&impolicy=stradivarius-itxmediumhigh&imwidth=572&imformat=chrome&imdensity=1", "price": "359,95 TL", "title": "D\u00f6k\u00fcml\u00fc spor \u015fort"}, {"infoUrl": "https://static.e-stradivarius.net/5/photos3/2023/V/0/1/p/7663/256/456/05/7663256456_8_1_4.jpg?t=1680507478219&impolicy=stradivarius-itxmediumhigh&imwidth=1162&imformat=chrome&imdensity=1", "price": "359,95 TL", "title": "Soluk efektli bisiklet\u00e7i tayt\u0131"}, {"infoUrl": "https://static.e-stradivarius.net/5/photos3/2023/V/0/1/p/1381/381/501/01/1381381501_8_1_4.jpg?t=1678118671507&impolicy=stradivarius-itxmediumhigh&imwidth=1162&imformat=chrome&imdensity=1", "price": "299,95 TL", "title": "D\u00f6k\u00fcml\u00fc spor \u015fort"}, {"infoUrl": "https://static.e-stradivarius.net/5/photos3/2023/V/0/1/p/7679/259/550/7679259550_1_1_1.jpg?t=1680512783051&impolicy=stradivarius-itxmediumhigh&imwidth=572&imformat=chrome&imdensity=1", "price": "299,95 TL", "title": "Diki\u015fsiz bal\u0131ks\u0131rt\u0131 spor k\u0131sa tayt"}, {"infoUrl": "https://static.e-stradivarius.net/5/photos3/2023/V/0/1/p/1249/848/004/05/1249848004_8_1_4.jpg?t=1678183023629&impolicy=stradivarius-itxmediumhigh&imwidth=1162&imformat=chrome&imdensity=1", "price": "299,95 TL", "title": "Spor hot pants"}, {"infoUrl": "https://static.e-stradivarius.net/5/photos3/2023/V/0/1/p/1249/848/004/1249848004_2_2_1.jpg?t=1677770862248&impolicy=stradivarius-itxmediumhigh&imwidth=572&imformat=chrome&imdensity=1", "price": "299,95 TL", "title": "Spor hot pants"}, {"infoUrl": "https://static.e-stradivarius.net/5/photos3/2023/V/0/1/p/7672/256/039/7672256039_1_1_1.jpg?t=1677770942363&impolicy=stradivarius-itxmediumhigh&imwidth=572&imformat=chrome&imdensity=1", "price": "359,95 TL", "title": "Soluk efektli pamuklu k\u0131sa tayt"}, {"infoUrl": "https://static.e-stradivarius.net/5/photos3/2023/V/0/1/p/7670/320/540/7670320540_1_1_1.jpg?t=1680512623421&impolicy=stradivarius-itxmediumhigh&imwidth=572&imformat=chrome&imdensity=1", "price": "359,95 TL", "title": "Kontrast fitilli \u015fort"}, {"infoUrl": "https://static.e-stradivarius.net/5/photos3/2023/V/0/1/p/7670/320/001/7670320001_1_1_1.jpg?t=1680512606629&impolicy=stradivarius-itxmediumhigh&imwidth=572&imformat=chrome&imdensity=1", "price": "359,95 TL", "title": "Kontrast fitilli \u015fort"}]