[{"infoUrl": "//lp2.hm.com/hmgoepprod?set=source[/3f/aa/3faad2e309550e1a809c0e008d6e4977327f9ca5.jpg],origin[dam],category[],type[LOOKBOOK],res[z],hmver[1]&call=url[file:/product/main]", "price": "389,99 TL", "title": "Relaxed Fit Kap\u00fc\u015fonlu ve Fermuarl\u0131 \u00dcst"}, {"infoUrl": "//lp2.hm.com/hmgoepprod?set=source[/da/80/da80bbc5d1b1bb9b69940f8dfdaf146f07c6dde0.jpg],origin[dam],category[],type[LOOKBOOK],res[z],hmver[1]&call=url[file:/product/main]", "price": "389,99 TL", "title": "Relaxed Fit Kap\u00fc\u015fonlu ve Fermuarl\u0131 \u00dcst"}, {"infoUrl": "//lp2.hm.com/hmgoepprod?set=source[/fc/d1/fcd1b834ec98821caa5f744ff15015a6f3a38cac.jpg],origin[dam],category[],type[LOOKBOOK],res[z],hmver[1]&call=url[file:/product/main]", "price": "349,99 TL", "title": "Relaxed Fit Sweatshirt"}, {"infoUrl": "//lp2.hm.com/hmgoepprod?set=source[/c3/d6/c3d688aa88c2fca8b6e19b9c8ef8e6b6aa931eba.jpg],origin[dam],category[],type[LOOKBOOK],res[z],hmver[1]&call=url[file:/product/main]", "price": "349,99 TL", "title": "Relaxed Fit Sweatshirt"}, {"infoUrl": "//lp2.hm.com/hmgoepprod?set=source[/bb/ad/bbad2c4ec8eb6aeda85e9eb2449a843d46c8cdc7.jpg],origin[dam],category[],type[LOOKBOOK],res[z],hmver[1]&call=url[file:/product/main]", "price": "699,99 TL", "title": "Oversized Fit Kap\u00fc\u015fonlu ve Fermuarl\u0131 \u00dcst"}, {"infoUrl": "//lp2.hm.com/hmgoepprod?set=source[/98/e9/98e99e2809c7e1e1a3edc3f6f98d7d3c4e54d386.jpg],origin[dam],category[],type[LOOKBOOK],res[z],hmver[1]&call=url[file:/product/main]", "price": "349,99 TL", "title": "Relaxed Fit Sweatshirt"}, {"infoUrl": "//lp2.hm.com/hmgoepprod?set=source[/89/6d/896dd97ce2f9563e3ef2f539b4a1d64e49302d82.jpg],origin[dam],category[],type[LOOKBOOK],res[z],hmver[1]&call=url[file:/product/main]", "price": "389,99 TL", "title": "Relaxed Fit Kap\u00fc\u015fonlu \u00dcst"}, {"infoUrl": "//lp2.hm.com/hmgoepprod?set=source[/59/35/5935a82f6199857d5e97b7aa7ca4c2ee3ac5dc07.jpg],origin[dam],category[],type[LOOKBOOK],res[z],hmver[1]&call=url[file:/product/main]", "price": "549,99 TL", "title": "Oversized Fit Pamuklu Sweatshirt"}, {"infoUrl": "//lp2.hm.com/hmgoepprod?set=source[/bf/1b/bf1b52ad1399df55446f24db5b6c424ed7761c0f.jpg],origin[dam],category[],type[LOOKBOOK],res[z],hmver[1]&call=url[file:/product/main]", "price": "579,99 TL", "title": "Oversized Fit Pamuklu ve Kap\u00fc\u015fonlu \u00dcst"}, {"infoUrl": "//lp2.hm.com/hmgoepprod?set=source[/23/8e/238ebec9e1120bd87e72a406fad1a569a10a7613.jpg],origin[dam],category[],type[LOOKBOOK],res[z],hmver[1]&call=url[file:/product/main]", "price": "579,99 TL", "title": "Oversized Fit Pamuklu ve Kap\u00fc\u015fonlu \u00dcst"}, {"infoUrl": "//lp2.hm.com/hmgoepprod?set=source[/00/b1/00b18be52c85bd790fadc26fdb21ad710c102041.jpg],origin[dam],category[],type[LOOKBOOK],res[z],hmver[1]&call=url[file:/product/main]", "price": "579,99 TL", "title": "Relaxed Fit Bask\u0131l\u0131 ve Kap\u00fc\u015fonlu \u00dcst"}, {"infoUrl": "//lp2.hm.com/hmgoepprod?set=source[/bc/63/bc63bad34fe5f8f2c83b85508734c64c99ea3937.jpg],origin[dam],category[],type[LOOKBOOK],res[z],hmver[1]&call=url[file:/product/main]", "price": "349,99 TL", "title": "Relaxed Fit Sweatshirt"}, {"infoUrl": "//lp2.hm.com/hmgoepprod?set=source[/14/a9/14a9b2766d18e934f43d4dd686ddb3e49d7ead5e.jpg],origin[dam],category[],type[LOOKBOOK],res[z],hmver[1]&call=url[file:/product/main]", "price": "389,99 TL", "title": "Relaxed Fit Kap\u00fc\u015fonlu \u00dcst"}, {"infoUrl": "//lp2.hm.com/hmgoepprod?set=source[/f4/11/f411b66a963a5cf0b54248e1cba4eda573a88d69.jpg],origin[dam],category[],type[LOOKBOOK],res[z],hmver[1]&call=url[file:/product/main]", "price": "389,99 TL", "title": "Relaxed Fit Kap\u00fc\u015fonlu \u00dcst"}, {"infoUrl": "//lp2.hm.com/hmgoepprod?set=source[/fc/80/fc80bb47f5eb1b882b52fd709882c691b0f1f581.jpg],origin[dam],category[],type[LOOKBOOK],res[z],hmver[1]&call=url[file:/product/main]", "price": "389,99 TL", "title": "Relaxed Fit Kap\u00fc\u015fonlu ve Fermuarl\u0131 \u00dcst"}, {"infoUrl": "//lp2.hm.com/hmgoepprod?set=source[/40/48/40482e71b768f11064a33e980faa004525679587.jpg],origin[dam],category[],type[LOOKBOOK],res[z],hmver[1]&call=url[file:/product/main]", "price": "389,99 TL", "title": "Relaxed Fit Kap\u00fc\u015fonlu \u00dcst"}, {"infoUrl": "//lp2.hm.com/hmgoepprod?set=source[/46/86/468622a6344c3cbb08d06fc0d82d59c7988a91a2.jpg],origin[dam],category[],type[LOOKBOOK],res[z],hmver[1]&call=url[file:/product/main]", "price": "249,99 TL", "title": "Regular Fit Kap\u00fc\u015fonlu \u00dcst"}, {"infoUrl": "//lp2.hm.com/hmgoepprod?set=source[/0b/68/0b686656d8b0c88062468e375d3cfe9bc316a415.jpg],origin[dam],category[],type[LOOKBOOK],res[z],hmver[1]&call=url[file:/product/main]", "price": "389,99 TL", "title": "Relaxed Fit Kap\u00fc\u015fonlu \u00dcst"}, {"infoUrl": "//lp2.hm.com/hmgoepprod?set=source[/7c/7e/7c7e9456d1662053d70b4584401e0d2280cceebd.jpg],origin[dam],category[],type[LOOKBOOK],res[m],hmver[1]&call=url[file:/product/style]", "price": "749,99 TL", "title": "Cep Detayl\u0131 Muflon Sweatshirt"}, {"infoUrl": "//lp2.hm.com/hmgoepprod?set=source[/ec/67/ec67213eee7b39e94de5260de4a675de8772e388.jpg],origin[dam],category[],type[LOOKBOOK],res[m],hmver[1]&call=url[file:/product/style]", "price": "389,99 TL", "title": "Relaxed Fit Kap\u00fc\u015fonlu \u00dcst"}, {"infoUrl": "//lp2.hm.com/hmgoepprod?set=source[/08/f0/08f020cf4df7b1db444cf233f47ac23922fc3970.jpg],origin[dam],category[],type[LOOKBOOK],res[m],hmver[1]&call=url[file:/product/style]", "price": "699,99 TL", "title": "Relaxed Fit \u00dcstte Fermuarl\u0131 Sweatshirt"}, {"infoUrl": "//lp2.hm.com/hmgoepprod?set=source[/4a/5d/4a5d933070dd1f05f6ace7d3d18d3ed00d78abbc.jpg],origin[dam],category[],type[LOOKBOOK],res[m],hmver[1]&call=url[file:/product/style]", "price": "579,99 TL", "title": "Oversized Fit Kap\u00fc\u015fonlu ve Fermuarl\u0131 \u00dcst"}, {"infoUrl": "//lp2.hm.com/hmgoepprod?set=source[/94/97/9497b99cc3ed61fc84b9c42e9e541d68ca420260.jpg],origin[dam],category[],type[LOOKBOOK],res[m],hmver[1]&call=url[file:/product/style]", "price": "499,99 TL", "title": "Oversized Fit Pamuklu Sweatshirt"}, {"infoUrl": "//lp2.hm.com/hmgoepprod?set=source[/d1/2d/d12d827e9968e28992914d14c211490f9b7bb83f.jpg],origin[dam],category[],type[LOOKBOOK],res[m],hmver[1]&call=url[file:/product/style]", "price": "579,99 TL", "title": "Relaxed Fit Bask\u0131l\u0131 ve Kap\u00fc\u015fonlu \u00dcst"}, {"infoUrl": "//lp2.hm.com/hmgoepprod?set=source[/45/6a/456aeb69a5c1400136fd79add30db17682f74fe6.jpg],origin[dam],category[],type[LOOKBOOK],res[z],hmver[1]&call=url[file:/product/main]", "price": "699,99 TL", "title": "Oversized Fit Kap\u00fc\u015fonlu ve Fermuarl\u0131 \u00dcst"}, {"infoUrl": "//lp2.hm.com/hmgoepprod?set=source[/71/9f/719f2a9e549a0eebdb175c6056da56c924ba8f14.jpg],origin[dam],category[],type[LOOKBOOK],res[z],hmver[1]&call=url[file:/product/main]", "price": "389,99 TL", "title": "Relaxed Fit Kap\u00fc\u015fonlu ve Fermuarl\u0131 \u00dcst"}, {"infoUrl": "//lp2.hm.com/hmgoepprod?set=source[/2a/4f/2a4f21bac14160844dfee46f87e3239c350113a5.jpg],origin[dam],category[],type[LOOKBOOK],res[z],hmver[1]&call=url[file:/product/main]", "price": "579,99 TL", "title": "Relaxed Fit Cep Detayl\u0131 Sweatshirt"}, {"infoUrl": "//lp2.hm.com/hmgoepprod?set=source[/36/87/36878e49a90b526f07cc6644650da65cddd3ad57.jpg],origin[dam],category[],type[LOOKBOOK],res[z],hmver[1]&call=url[file:/product/main]", "price": "619,99 TL", "title": "Oversized Fit Pamuklu ve Kap\u00fc\u015fonlu \u00dcst"}, {"infoUrl": "//lp2.hm.com/hmgoepprod?set=source[/ac/41/ac416218726238c437079579313f31942efd7d92.jpg],origin[dam],category[],type[LOOKBOOK],res[z],hmver[1]&call=url[file:/product/main]", "price": "559,99 TL", "title": "Essentials No 3: THE HOODIE"}, {"infoUrl": "//lp2.hm.com/hmgoepprod?set=source[/58/c0/58c0965f9c1e48de2c5e98e48762880965d0395b.jpg],origin[dam],category[],type[LOOKBOOK],res[z],hmver[1]&call=url[file:/product/main]", "price": "499,99 TL", "title": "Essentials No 11: THE SWEATSHIRT"}, {"infoUrl": "//lp2.hm.com/hmgoepprod?set=source[/ac/12/ac128f7b05fae8281bc28cd01fefd9307ae08f8b.jpg],origin[dam],category[],type[LOOKBOOK],res[z],hmver[1]&call=url[file:/product/main]", "price": "649,99 TL", "title": "DryMove\u2122 Spor Sweatshirt'\u00fc"}, {"infoUrl": "//lp2.hm.com/hmgoepprod?set=source[/62/9b/629b4e8939d06f8f115bf13a308003cefeae900c.jpg],origin[dam],category[],type[LOOKBOOK],res[z],hmver[1]&call=url[file:/product/main]", "price": "389,99 TL", "title": "Relaxed Fit Kap\u00fc\u015fonlu \u00dcst"}, {"infoUrl": "//lp2.hm.com/hmgoepprod?set=source[/f9/9f/f99f38979c01f7c347a20898a694840ca7322526.jpg],origin[dam],category[],type[LOOKBOOK],res[z],hmver[1]&call=url[file:/product/main]", "price": "579,99 TL", "title": "Relaxed Fit Bask\u0131l\u0131 ve Kap\u00fc\u015fonlu \u00dcst"}, {"infoUrl": "//lp2.hm.com/hmgoepprod?set=source[/59/7c/597c70ef712ef86389e78e3d55785c60b81516ca.jpg],origin[dam],category[],type[LOOKBOOK],res[z],hmver[1]&call=url[file:/product/main]", "price": "579,99 TL", "title": "Relaxed Fit Bask\u0131l\u0131 ve Kap\u00fc\u015fonlu \u00dcst"}, {"infoUrl": "//lp2.hm.com/hmgoepprod?set=source[/30/7f/307f3e1ff0485958df5943baff96c3ae905d3564.jpg],origin[dam],category[],type[LOOKBOOK],res[z],hmver[1]&call=url[file:/product/main]", "price": "579,99 TL", "title": "Relaxed Fit Rugby Ti\u015f\u00f6rt\u00fc"}, {"infoUrl": "//lp2.hm.com/hmgoepprod?set=source[/cf/0d/cf0daf40158a7957d2034c294b5ebb2f0843d30a.jpg],origin[dam],category[],type[LOOKBOOK],res[z],hmver[1]&call=url[file:/product/main]", "price": "649,99 TL", "title": "DryMove\u2122 Spor Sweatshirt'\u00fc"}]